[{"id":"Temp","device":"HQP","address":"0O","serial":"001Uc","haddr":"PROM-HQP-T-0O","name":"Temperatura w gabinecie","value":"19.66","type":"T.0","io":"t","active":1,"eval":null,"store":"temp_syp/300","unit":"°C","related":["PROM-ADD-06a4b9ca"],"_updated":1613887894504,"last":1613887894504,"time":59057,"t_h_comfort":"20.5","t_h_eco":"20","t_h_nofrost":"15","t_h_cool":"30","t_h_hysteresis":"0.15","t_comfort":"20.6","t_eco":"17.5","t_nofrost":"17","t_cool":"30","t_hysteresis":"0.15","temp_change":1,"lastValue":"19.66","change":-1,"unitValue":"19.66 °C","sh_type":"","sh_traits":"","sh_nicks":"","t_rel":null},{"id":"R.Pr.P","device":"HQP","address":"03","haddr":"PROM-HQP-R-03","serial":"000A3","name":"Roleta sypialnia górna prawa","value":"stop-u","timeout":"31","io":"r","active":1,"_updated":1612683399879,"type":"","gpf":"","last":1612683399879,"eval":null,"time":31048,"store":"","unit":"","related":null,"lastValue":"up","t_comfort":"","t_eco":"","t_nofrost":"","t_cool":"","t_hysteresis":"","t_rel":null,"change":0,"sh_type":"BLINDS","sh_traits":"OpenClose","sh_nicks":"right blind"},{"id":"R.Pr.L","device":"HQP","address":"04","haddr":"PROM-HQP-R-04","serial":"000A2","name":"Roleta sypialnia górna lewa","value":"stop-u","timeout":"35","io":"r","active":1,"type":"","gpf":"","_updated":1612683401838,"last":1612683401838,"eval":null,"time":31050,"store":"","unit":"","related":null,"lastValue":"up","t_comfort":"","t_eco":"","t_nofrost":"","t_cool":"","t_hysteresis":"","t_rel":null,"change":0,"sh_type":"BLINDS","sh_traits":"OpenClose","sh_nicks":"left blind"},{"id":"R.Sy.L","device":"HQP","address":"0A","haddr":"PROM-HQP-R-0A","serial":"000Qf","name":"Roleta gabinet lewa","value":"stop-u","timeout":"50","io":"r","active":1,"type":"","gpf":"","_updated":1613833973240,"related":null,"last":1613833973240,"eval":null,"time":50048,"store":"","unit":"","lastValue":"up","change":0,"sh_type":"BLINDS","sh_traits":"OpenClose","sh_nicks":"left blind","t_comfort":"","t_eco":"","t_nofrost":"","t_cool":"","t_hysteresis":"","t_rel":null},{"id":"R.La","device":"HQP","address":"0C","haddr":"PROM-HQP-R-0C","serial":"000QZ","name":"Roleta parter łazienka","value":"stop-d","timeout":"55","io":"r","active":1,"type":"","gpf":"","_updated":1613837455440,"last":1613837455440,"eval":null,"time":50398878,"lastValue":"down","change":0},{"id":"R.Pi","device":"HQP","address":"0D","haddr":"PROM-HQP-R-0D","serial":"000Qa","name":"Roleta Janusz","value":"stop-u","timeout":"55","io":"r","active":1,"type":"","gpf":"","_updated":1613833849876,"last":1613833849876,"eval":null,"time":55050,"lastValue":"up","change":0,"unit":"","sh_type":"BLINDS","sh_traits":"OpenClose","sh_nicks":"Janus blind","t_comfort":"","t_eco":"","t_nofrost":"","t_cool":"","t_hysteresis":"","store":"","related":null,"t_rel":null},{"id":"R.Sy.P","device":"HQP","address":"01","haddr":"PROM-HQP-R-01","serial":"000Qb","name":"Roleta gabinet prawa","value":"stop-u","timeout":"60","io":"r","active":1,"type":"","gpf":"","_updated":1613833973612,"related":null,"last":1613833973612,"eval":null,"time":50050,"store":"","unit":"","lastValue":"up","change":0,"sh_type":"BLINDS","sh_traits":"OpenClose","sh_nicks":"right blind","t_comfort":"","t_eco":"","t_nofrost":"","t_cool":"","t_hysteresis":"","t_rel":null},{"id":"R.P.Kor","device":"HQP","address":"0F","haddr":"PROM-HQP-R-0F","serial":"000A1","name":"Roleta korytarz","value":"stop-u","timeout":"75","io":"r","active":1,"type":"","gpf":"","_updated":1613833992284,"last":1613833992284,"eval":null,"time":75048,"lastValue":"up","change":0},{"id":"R.Pr.T","device":"HQP","address":"0B","haddr":"PROM-HQP-R-0B","serial":"000Qe","name":"Roleta sypialnia taras","value":"stop-u","timeout":"75","io":"r","active":1,"_updated":1613887054027,"type":"","gpf":"","related":null,"last":1613887054027,"eval":null,"time":770300,"store":"","unit":"","t_comfort":"","t_eco":"","t_nofrost":"","t_cool":"","t_hysteresis":"","lastValue":"up","change":0,"t_rel":null,"sh_type":"BLINDS","sh_traits":"OpenClose","sh_nicks":"blind"},{"id":"R.Sa.P","device":"HQP","address":"02","haddr":"PROM-HQP-R-02","serial":"000Qc","name":"Roleta salon, prawa","value":"stop-u","timeout":"75","io":"r","active":1,"type":"","gpf":"","_updated":1613833401622,"related":null,"last":1613833401622,"eval":null,"time":50050,"lastValue":"up","change":0,"unit":"","sh_type":"BLINDS","sh_traits":"OpenClose","sh_nicks":"right blind","t_comfort":"","t_eco":"","t_nofrost":"","t_cool":"","t_hysteresis":"","store":"","t_rel":null},{"id":"R.Sc.P","device":"HQP","address":"08","haddr":"PROM-HQP-R-08","serial":"000QY","name":"Roleta schody piętro, prawa","value":"stop-u","timeout":"41","io":"r","active":1,"type":"","gpf":"","_updated":1609515318368,"last":1609515318368,"eval":null,"time":958,"lastValue":"stop-u","change":0},{"id":"R.Ku","device":"HQP","address":"0E","haddr":"PROM-HQP-R-0E","serial":"000Qk","name":"Roleta kuchnia","value":"stop-u","timeout":"85","io":"r","active":1,"type":"","gpf":"","_updated":1613833674404,"related":null,"last":1613833674404,"eval":null,"time":85050,"lastValue":"up","change":0,"unit":"","sh_type":"BLINDS","sh_traits":"OpenClose","sh_nicks":"kitchen blind","t_comfort":"","t_eco":"","t_nofrost":"","t_cool":"","t_hysteresis":"","store":"","t_rel":null},{"id":"R.Sa.L","device":"HQP","address":"09","haddr":"PROM-HQP-R-09","serial":"000Qj","name":"Roleta salon, lewa","value":"stop-u","timeout":"90","io":"r","active":1,"type":"","gpf":"","_updated":1613833651684,"related":null,"last":1613833651684,"eval":null,"time":40048,"lastValue":"up","change":0,"unit":"","sh_type":"BLINDS","sh_traits":"OpenClose","sh_nicks":"left blind","t_comfort":"","t_eco":"","t_nofrost":"","t_cool":"","t_hysteresis":"","store":"","t_rel":null},{"id":"R.P.L","device":"HQP","address":"0N","haddr":"PROM-HQP-R-0N","serial":"000QK","name":"Roleta piętro łazienka","value":"stop-u","timeout":"55","io":"r","active":1,"type":"","gpf":"","_updated":1613833691994,"last":1613833691994,"eval":null,"time":55049,"lastValue":"up","change":0},{"id":"R.Pi.T","device":"HQP","address":"0M","haddr":"PROM-HQP-R-0M","serial":"000QI","name":"Roleta piętro taras","value":"stop-u","timeout":"75","io":"r","active":1,"type":"","gpf":"","_updated":1613833734722,"last":1613833734721,"eval":null,"time":75047,"lastValue":"up","change":0},{"id":"R.ScP.L","device":"HQP","address":"06","haddr":"PROM-HQP-R-06","serial":"000Ql","name":"Roleta schody piwnica, lewa","value":"stop-u","timeout":"41","io":"r","active":1,"type":"","gpf":"","_updated":1612767539257,"last":1612767539257,"eval":null,"time":41049,"lastValue":"up","change":0},{"id":"R.ScP.P","device":"HQP","address":"05","haddr":"PROM-HQP-R-05","serial":"000Qd","name":"Roleta schody piwnica, prawa","value":"stop-d","timeout":"41","io":"r","active":1,"type":"","gpf":"","_updated":1611513881998,"last":1611513881998,"eval":null,"time":41048,"lastValue":"down","change":0},{"id":"R.Sc.L","device":"HQP","address":"07","haddr":"PROM-HQP-R-07","serial":"000Qo","name":"Roleta schody piętro, lewa","value":"stop-u","timeout":"41","io":"r","active":1,"type":"","gpf":"","_updated":1609515358666,"last":1609515358666,"eval":null,"time":278,"lastValue":"stop-u","change":0},{"id":"44","device":"HQP","address":"0I.6","haddr":"PROM-HQP-O-0I.6","parent":"0I","name":"Lampki podłogowe taras","value":0,"timeout":"0","type":"S","io":"o","active":"0"},{"id":"CO","device":"HQP","address":"0K.5","haddr":"PROM-HQP-O-0K.5","parent":"0K","name":"Kaloryfery w piwnicy","value":"0","timeout":"0","type":"W","io":"o","active":"1","unit":"","eval":null,"store":"","t_comfort":"","t_eco":"","t_nofrost":"","t_cool":"","t_hysteresis":"","related":["PR.GRP.1c758ac6"],"_updated":1613887895501,"last":1613887895501,"time":61041,"temp_change":"","lastValue":"0","change":0,"unitValue":"0"},{"id":"25","device":"HQP","address":"0K.3","haddr":"PROM-HQP-O-0K.3","parent":"0K","name":"Altana","value":"0","timeout":"","type":"0","io":"o","active":"1","eval":null,"store":"","related":null,"_updated":1613849795826,"last":1613849795826,"time":600035,"unit":"","t_comfort":"","t_eco":"","t_nofrost":"","t_cool":"","t_hysteresis":"","lastValue":"1","change":1,"unitValue":"0"},{"id":"","device":"HQP","address":"0I.0","haddr":"PROM-HQP-O-0I.0","parent":"0I","name":"Lampki na rynnie","value":"0","timeout":"0","type":"Z","io":"o","active":"1","last":1535459927304,"eval":null,"time":11055,"_updated":1535459927305,"lastValue":"1"},{"id":"42","device":"HQP","address":"0H.0","haddr":"PROM-HQP-O-0H.0","parent":"0H","name":"X-nic potrzebne na dobranoc","value":0,"timeout":"0","type":"X","io":"o","active":"1"},{"id":"40","device":"HQP","address":"0L.7","haddr":"PROM-HQP-O-0L.7","parent":"0L","name":"Lampki ścienne taras","value":"0","timeout":"0","type":"S","io":"o","active":true,"_updated":1468355445870},{"id":"S.TarS","device":"HQP","address":"0J.8","haddr":"PROM-HQP-O-0J.8","parent":"0J","name":"Taras - ściana salonowa","value":"0","timeout":"0","type":"Z","io":"o","active":"1","_updated":1609444070757,"last":1609444070757,"eval":null,"time":770807,"lastValue":"1","change":0},{"id":"S.TarB","device":"HQP","address":"0J.9","haddr":"PROM-HQP-O-0J.9","parent":"0J","name":"Taras - ściana boczna","value":"0","timeout":"0","type":"Z","io":"o","active":"1","_updated":1605798690278,"last":1605798690278,"eval":null,"time":2506,"lastValue":"1","change":0},{"id":"35","device":"HQP","address":"0I.8","haddr":"PROM-HQP-O-0I.8","parent":"0I","name":"Piętro łazienka kinkiet","value":"0","timeout":"600","type":"S","io":"o","active":"1","gpf":"","_updated":1613833635148,"last":1613833635148,"eval":null,"time":767,"lastValue":"1","change":0},{"id":"22","device":"HQP","address":"0L.4","haddr":"PROM-HQP-O-0L.4","parent":"0L","name":"Światło piętro korytarz od antresoli","value":"0","timeout":"7200","type":"S","io":"o","active":"1","gpf":"","_updated":1613848004850,"related":["PROM-ADD-4d4dc234"],"last":1613848004850,"eval":null,"time":3075929,"lastValue":"1","change":0},{"id":"41","device":"HQP","address":"0K.0","haddr":"PROM-HQP-O-0K.0","parent":"0K","name":"Christmas - Podlewanie / zimą choinka","value":"0","timeout":"0","type":"","io":"o","active":"1","eval":null,"store":"","related":null,"_updated":1608816341462,"last":1608816341461,"time":1124008910,"unit":"","t_comfort":"","t_eco":"","t_nofrost":"","t_cool":"","t_hysteresis":"","lastValue":"1","change":-1,"unitValue":"1","sh_type":"","sh_traits":"","sh_nicks":"","t_rel":null},{"id":"31","device":"HQP","address":"0J.2","haddr":"PROM-HQP-O-0J.2","parent":"0J","name":"Światło schody piętro","value":"0","timeout":"45","type":"S","io":"o","active":"1","gpf":"","_updated":1613845706489,"related":["PROM-ADD-4d4dc234"],"last":1613845706489,"eval":null,"time":60036,"lastValue":"1","change":0},{"id":"32","device":"HQP","address":"0L.1","haddr":"PROM-HQP-O-0L.1","parent":"0L","name":"Światło piętro Tomek kinkiet","value":"0","timeout":"7200","type":"S","io":"o","active":"1","_updated":1613848392061,"gpf":"","related":["PROM-ADD-4d4dc234"],"last":1613848392061,"eval":null,"time":7875,"lastValue":"1","unit":"","t_comfort":"","t_eco":"","t_nofrost":"","t_cool":"","t_hysteresis":"","store":"","change":0,"sh_type":"","sh_traits":"","sh_nicks":"","t_rel":null},{"id":"43","device":"HQP","address":"0I.7","haddr":"PROM-HQP-O-0I.7","parent":"0I","name":"Światło piętro Seba prawe","value":"0","timeout":"7200","type":"S","io":"o","active":"1","_updated":1613843687402,"gpf":"","related":["PROM-ADD-4d4dc234"],"last":1613843687402,"eval":null,"time":3362144,"lastValue":"1","change":0},{"id":"20","device":"HQP","address":"0L.6","haddr":"PROM-HQP-O-0L.6","parent":"0L","name":"Światło piętro Marcin kinkiet","value":"0","timeout":"3600","type":"S","io":"o","active":"1","_updated":1613849081187,"gpf":"","related":["PROM-ADD-4d4dc234"],"last":1613849081187,"eval":null,"time":4149545,"lastValue":"1","change":0,"unit":"","sh_type":"","sh_traits":"","sh_nicks":"","t_comfort":"","t_eco":"","t_nofrost":"","t_cool":"","t_hysteresis":"","store":"","t_rel":null},{"id":"45","device":"HQP","address":"0I.5","haddr":"PROM-HQP-O-0I.5","parent":"0I","name":"Światło piętro Marcin ślepy kabelek","value":"0","timeout":"3600","type":"S","io":"o","active":"1","_updated":1568740763629,"gpf":"","related":["PROM-ADD-4d4dc234"],"last":1568740763629,"eval":null,"time":39322,"lastValue":"1","change":0,"unit":"","sh_type":"","sh_traits":"","sh_nicks":"","t_comfort":"","t_eco":"","t_nofrost":"","t_cool":"","t_hysteresis":"","store":"","t_rel":null},{"id":"21","device":"HQP","address":"0L.5","haddr":"PROM-HQP-O-0L.5","parent":"0L","name":"Światło piętro Seba lewe","value":"0","timeout":"3600","type":"S","io":"o","active":"1","_updated":1613843686595,"gpf":"","related":["PROM-ADD-4d4dc234"],"last":1613843686595,"eval":null,"time":3360598,"lastValue":"1","change":0},{"id":"BRAMA","device":"HQP","address":"0P.9","haddr":"PROM-HQP-O-0P.0","parent":"0P","name":"Brama","value":"0","timeout":"0","type":"B","io":"o","active":"1","_updated":1613843867978,"last":1613843867978,"eval":null,"time":3035,"store":"","unit":"","related":null,"lastValue":"1","change":0,"sh_type":"GATE","sh_traits":"OpenClose","sh_nicks":"gate","t_comfort":"","t_eco":"","t_nofrost":"","t_cool":"","t_hysteresis":"","t_rel":null},{"id":"36","device":"HQP","address":"0J.5","haddr":"PROM-HQP-O-0J.5","parent":"0J","name":"Światło parter łazienka kinkiet","value":"0","timeout":"900","type":"S","io":"o","active":"1","_updated":1613887247499,"gpf":"","related":["PROM-ADD-e8bf55cb"],"last":1613887247499,"eval":null,"time":28789281,"lastValue":"0","change":0,"unitValue":"0"},{"id":"24","device":"HQP","address":"0K.4","haddr":"PROM-HQP-O-0K.4","parent":"0K","name":"Wentylator piwnica","value":"0","timeout":"0","type":"0","io":"o","active":"1","_updated":1613887825375,"last":1613887825374,"eval":null,"time":109168,"store":"","related":null,"unit":"","t_comfort":"","t_eco":"","t_nofrost":"","t_cool":"","t_hysteresis":"","lastValue":"0","_alias":"fan","change":0,"unitValue":"0"},{"id":"FUR","device":"HQP","address":"0P.2","haddr":"PROM-HQP-O-0P.2","parent":"0P","name":"Furtka","value":"0","timeout":"0","type":"B","io":"o","active":"1","_updated":1612956562383,"last":1612956562383,"eval":null,"time":5038,"store":"","unit":"","related":null,"lastValue":"1","change":0,"sh_type":"DOOR","sh_traits":"OpenClose","sh_nicks":"wicket","t_comfort":"","t_eco":"","t_nofrost":"","t_cool":"","t_hysteresis":"","t_rel":null},{"id":"7","device":"HQP","address":"0G.7","haddr":"PROM-HQP-O-0G.7","parent":"0G","name":"Światło sypialnia","value":"0","timeout":"3600","type":"S","io":"o","active":"1","gpf":"","_updated":1613853593183,"related":["PROM-ADD-e8bf55cb"],"last":1613853593182,"eval":null,"time":3490738,"unit":"","store":"","t_comfort":"","t_eco":"","t_nofrost":"","t_cool":"","t_hysteresis":"","lastValue":"1","change":0,"t_rel":null,"sh_type":"LIGHT","sh_traits":"OnOff","sh_nicks":"bedroom light"},{"id":"9","device":"HQP","address":"0J.3","haddr":"PROM-HQP-O-0J.3","parent":"0J","name":"Światło parter korytarz","value":"0","timeout":"900","type":"S","io":"o","active":"1","gpf":"","_updated":1613858477261,"related":["PROM-ADD-e8bf55cb"],"last":1613858477261,"eval":null,"time":28148801,"unit":"","t_comfort":"","t_eco":"","t_nofrost":"","t_cool":"","t_hysteresis":"","store":"","lastValue":"1","change":0},{"id":"8","device":"HQP","address":"0G.6","haddr":"PROM-HQP-O-0G.6","parent":"0G","name":"Światło salon nad stołem","value":"0","timeout":"1800","type":"S","io":"o","active":"1","_updated":1613847961698,"gpf":"","related":["PROM-ADD-e8bf55cb"],"last":1613847961698,"eval":null,"time":244,"lastValue":"1","change":0,"unit":"","sh_type":"LIGHT","sh_traits":"OnOff","sh_nicks":"table light","t_comfort":"","t_eco":"","t_nofrost":"","t_cool":"","t_hysteresis":"","store":"","t_rel":null},{"id":"19","device":"HQP","address":"0I.9","haddr":"PROM-HQP-O-0I.9","parent":"0I","name":"Światło piętro łazienka górna","value":"0","timeout":"5400","type":"S","io":"o","active":"1","gpf":"","_updated":1613848001874,"last":1613848001874,"eval":null,"time":26214,"lastValue":"1","change":-1,"unitValue":"1"},{"id":"30","device":"HQP","address":"0L.0","haddr":"PROM-HQP-O-0L.0","parent":"0L","name":"Schody - lampki","value":"0","timeout":"60","type":"S","io":"o","active":"1","gpf":"","_updated":1613845707119,"related":["PROM-ADD-4d4dc234"],"last":1613845707119,"eval":null,"time":60036,"lastValue":"1","change":0},{"id":"18","device":"HQP","address":"0L.8","haddr":"PROM-HQP-O-0L.8","parent":"0L","name":"Światło piętro Tomek górne","value":"0","timeout":"7200","type":"S","io":"o","active":"1","_updated":1613848368004,"gpf":"","related":["PROM-ADD-4d4dc234"],"last":1613848368003,"eval":null,"time":1220,"lastValue":"1","unit":"","t_comfort":"","t_eco":"","t_nofrost":"","t_cool":"","t_hysteresis":"","store":"","change":0,"sh_type":"","sh_traits":"","sh_nicks":"","t_rel":null},{"id":"23","device":"HQP","address":"0L.3","haddr":"PROM-HQP-O-0L.3","parent":"0L","name":"Światło piętro korytarz od tarasu","value":"0","timeout":"1800","type":"S","io":"o","active":"1","gpf":"","_updated":1613850884328,"related":["PROM-ADD-4d4dc234"],"last":1613850884328,"eval":null,"time":1800036,"lastValue":"1","change":0},{"id":"14","device":"HQP","address":"0G.0","haddr":"PROM-HQP-O-0G.0","parent":"0G","name":"Światło Janusz","value":"0","timeout":"10800","type":"S","io":"o","active":"1","gpf":"","_updated":1613848103137,"related":["PROM-ADD-e8bf55cb"],"last":1613848103137,"eval":null,"time":3287,"lastValue":"1","change":0,"unit":"","sh_type":"LIGHT","sh_traits":"OnOff","sh_nicks":"Janus light,światło u Janusza","t_comfort":"","t_eco":"","t_nofrost":"","t_cool":"","t_hysteresis":"","store":"","t_rel":null},{"id":"17","device":"HQP","address":"0L.9","haddr":"PROM-HQP-O-0L.9","parent":"0L","name":"Światło garderoba piętro","value":"0","timeout":"0","type":"S","io":"o","active":"1","_updated":1613241563491,"gpf":"","related":["PROM-ADD-4d4dc234"],"last":1613241563491,"eval":null,"time":44201,"lastValue":"0","unit":"","t_comfort":"","t_eco":"","t_nofrost":"","t_cool":"","t_hysteresis":"","store":"","change":-1,"unitValue":"1"},{"id":"GAZ.CW","device":"HQP","address":"0P.4","haddr":"PROM-HQP-O-0P.4","parent":"0P","name":"Sterowanie piecem gaz CW","value":"0","timeout":"0","type":"0","io":"o","active":"1","_updated":1613887894561,"last":1613887894561,"eval":null,"time":60059,"store":"","related":["PR.GRP.ab52b4e6"],"unit":"","t_comfort":"","t_eco":"","t_nofrost":"","t_cool":"","t_hysteresis":"","lastValue":"0","_alias":"hwgo","change":-1,"unitValue":"1"},{"id":"ŁA.Dio","device":"HQP","address":"0H.3","haddr":"PROM-HQP-O-0H.3","parent":"0H","name":"Łazienka dolna - dioda","value":"0","timeout":"0","type":"S","io":"o","active":"1","_updated":1613856608804,"last":1613856608804,"eval":null,"time":6128011,"lastValue":"0","change":1,"unitValue":"0"},{"id":"ZCW","device":"HQP","address":"0K.1","haddr":"PROM-HQP-O-0K.1","parent":"0K","name":"Zawór grzania ciepłej wody - nieużywany","value":"0","timeout":"0","type":"0","io":"o","active":"1","gpf":"","_updated":1492537202246,"last":1492536699435,"eval":"","time":1800023,"store":"","related":null,"unit":"","t_comfort":"","t_eco":"","t_nofrost":"","t_cool":"","t_hysteresis":""},{"id":"39","device":"HQP","address":"0J.7","haddr":"PROM-HQP-O-0J.7","parent":"0J","name":"Salon nad kanapą","value":"0","timeout":"25000","type":"S","io":"o","active":"1","gpf":"","_updated":1613236865171,"related":["PROM-ADD-e8bf55cb"],"last":1613236865171,"eval":null,"time":247223458,"unit":"","t_comfort":"","t_eco":"","t_nofrost":"","t_cool":"","t_hysteresis":"","store":"","lastValue":"0","change":0,"unitValue":"1","t_rel":null,"sh_type":"LIGHT","sh_traits":"OnOff","sh_nicks":" couch light"},{"id":"29","device":"HQP","address":"0J.1","haddr":"PROM-HQP-O-0J.1","parent":"0J","name":"Światło salon od korytarza","value":"0","timeout":"7200","type":"S","io":"o","active":"1","_updated":1613847962430,"gpf":"","related":["PROM-ADD-e8bf55cb"],"eval":null,"last":1613847962430,"time":245,"lastValue":"1","change":-1,"unitValue":"1","unit":"","sh_type":"LIGHT","sh_traits":"OnOff","sh_nicks":"back light","t_comfort":"","t_eco":"","t_nofrost":"","t_cool":"","t_hysteresis":"","store":"","t_rel":null},{"id":"2","device":"HQP","address":"0K.9","haddr":"PROM-HQP-O-0K.9","parent":"0K","name":"Światło sauna","value":"0","timeout":"3600","type":"0","io":"o","active":"1","_updated":1613887636975,"gpf":"","related":["PROM-ADD-164372de"],"last":1613887636975,"eval":null,"time":306591,"store":"","lastValue":"1","change":-1,"unitValue":"1"},{"id":"11","device":"HQP","address":"0G.3","haddr":"PROM-HQP-O-0G.3","parent":"0G","name":"Światło gabinet","value":"0","timeout":"1800","type":"","io":"o","active":"1","_updated":1613850631125,"gpf":"","related":["PROM-ADD-e8bf55cb"],"last":1613850631125,"eval":null,"time":1552317,"lastValue":"1","unit":"","t_comfort":"","t_eco":"","t_nofrost":"","t_cool":"","t_hysteresis":"","store":"","change":0,"sh_type":"LIGHT","sh_traits":"OnOff","sh_nicks":"office light","t_rel":null},{"id":"12","device":"HQP","address":"0G.2","haddr":"PROM-HQP-O-0G.2","parent":"0G","name":"Światło schody piwnica","value":"0","timeout":"60","type":"S","io":"o","active":"1","_updated":1613850053551,"gpf":"","related":null,"last":1613850053551,"eval":null,"time":8698,"unit":"","store":"","t_comfort":"","t_eco":"","t_nofrost":"","t_cool":"","t_hysteresis":"","lastValue":"1","change":1,"unitValue":"0"},{"id":"13","device":"HQP","address":"0G.1","haddr":"PROM-HQP-O-0G.1","parent":"0G","name":"Światło łazienka","value":"0","timeout":"5400","type":"S","io":"o","active":"1","_updated":1613887247457,"gpf":"","related":["PROM-ADD-e8bf55cb"],"last":1613887247457,"eval":null,"time":78713,"store":"","unit":"","lastValue":"1","change":-1,"unitValue":"1","sh_type":"LIGHT","sh_traits":"OnOff","sh_nicks":"bathroom light","t_comfort":"","t_eco":"","t_nofrost":"","t_cool":"","t_hysteresis":"","t_rel":null},{"id":"52","device":"HQP","address":"0P.1","haddr":"PROM-HQP-O-0P.1","parent":"0P","name":"Rozbrojenie szopy","value":"1","timeout":"0","type":"S","io":"o","active":"1","_updated":1613883630790,"related":null,"eval":null,"last":1613883630790,"time":25822913,"lastValue":"0","change":0},{"id":"GAZ.CO","device":"HQP","address":"0P.3","haddr":"PROM-HQP-O-0P.3","parent":"0P","name":"Sterowanie piecem gaz CO","value":"1","timeout":"0","type":"0","io":"o","active":"1","_updated":1613885089994,"eval":null,"store":"","related":["PR.GRP.ab52b4e6"],"last":1613885089994,"time":58,"unit":"","t_comfort":"","t_eco":"","t_nofrost":"","t_cool":"","t_hysteresis":"","lastValue":"1","_alias":"cogo","change":-1,"unitValue":"1"},{"id":"3","device":"HQP","address":"0K.8","haddr":"PROM-HQP-O-0K.8","parent":"0K","name":"Światło bilard + szafa","value":"0","timeout":"4600","type":"S","io":"o","active":"1","_updated":1613887642416,"gpf":"","related":["PROM-ADD-164372de"],"last":1613887642416,"eval":null,"time":192,"lastValue":"0","change":0},{"id":"FLPOMP","device":"HQP","address":"0J.6","haddr":"PROM-HQP-O-0J.6","parent":"0J","name":"Pompa podłogówki jako kaloryfer","value":"1","timeout":"0","type":"P","io":"o","active":"1","last":1613887894589,"eval":null,"time":40,"_updated":1613887894590,"related":["PR.GRP.1c758ac6"],"unit":"","store":"","t_comfort":"","t_eco":"","t_nofrost":"","t_cool":"","t_hysteresis":"","lastValue":"1","change":1,"unitValue":"0"},{"id":"27","device":"HQP","address":"0L.2","haddr":"PROM-HQP-O-0L.2","parent":"0L","name":"Podłogówka górna łazienka","value":"1","timeout":"0","type":"O","io":"o","active":"1","gpf":"","_updated":1613883636740,"last":1613883636740,"eval":null,"time":86422309,"lastValue":"1","change":0},{"id":"16","device":"HQP","address":"0G.9","haddr":"PROM-HQP-O-0G.9","parent":"0G","name":"Kinkiet przed wejściem","value":"0","timeout":"0","type":"Z","io":"o","active":"1","_updated":1613110328508,"eval":null,"last":1613110328508,"time":51765129,"lastValue":"1","change":0,"unitValue":"1","unit":"","sh_type":"","sh_traits":"","sh_nicks":"","t_comfort":"","t_eco":"","t_nofrost":"","t_cool":"","t_hysteresis":"","store":"","related":null,"t_rel":null},{"id":"OGR","device":"HQP","address":"0P.7","haddr":"PROM-HQP-O-0P.7","parent":"0P","name":"Oświetlenie ogrodu","value":"0","timeout":"0","type":"Z","io":"o","active":"1","last":1613886753517,"eval":null,"time":28944694,"_updated":1613886753518,"unit":"","t_comfort":"","t_eco":"","t_nofrost":"","t_cool":"","t_hysteresis":"","store":"","related":null,"lastValue":"0","change":0},{"id":"26","device":"HQP","address":"0K.2","haddr":"PROM-HQP-O-0K.2","parent":"0K","name":"Cyrkulacja ciepłej wody","value":"0","timeout":"300","type":"","io":"o","active":"1","_updated":1613887854402,"gpf":"","eval":null,"last":1613887854402,"time":30037,"store":"","related":null,"lastValue":"1","change":-1,"unitValue":"1","unit":"","sh_type":"","sh_traits":"","sh_nicks":"","t_comfort":"","t_eco":"","t_nofrost":"","t_cool":"","t_hysteresis":"","t_rel":null},{"id":"34","device":"HQP","address":"0J.4","haddr":"PROM-HQP-O-0J.4","parent":"0J","name":"Światło parter garderoba","value":"0","timeout":"0","type":"S","io":"o","active":"1","_updated":1613847815680,"gpf":"","related":["PROM-ADD-e8bf55cb"],"last":1613847815680,"eval":null,"time":24252,"lastValue":"1","change":0},{"id":"5","device":"HQP","address":"0K.6","haddr":"PROM-HQP-O-0K.6","parent":"0K","name":"Bilard światlo lewe","value":"0","timeout":"5400","type":"0","io":"o","active":"1","_updated":1613887641946,"gpf":"","related":["PROM-ADD-164372de"],"last":1613887641946,"eval":null,"time":470,"store":"","lastValue":"0","change":1,"unitValue":"0"},{"id":"15","device":"HQP","address":"0G.8","haddr":"PROM-HQP-O-0G.8","parent":"0G","name":"Światło wiatrołap","value":"0","timeout":"120","type":"S","io":"o","active":true,"gpf":"","_updated":1613849790828,"related":["PROM-ADD-e8bf55cb"],"last":1613849790828,"eval":null,"time":600037,"unit":"","t_comfort":"","t_eco":"","t_nofrost":"","t_cool":"","t_hysteresis":"","store":"","lastValue":"1","change":-1,"unitValue":"1","sh_type":"","sh_traits":"","sh_nicks":"","t_rel":null},{"id":"28","device":"HQP","address":"0J.0","haddr":"PROM-HQP-O-0J.0","parent":"0J","name":"Światło spiżarnia","value":"1","timeout":"","type":"S","io":"o","active":"1","_updated":1613887902168,"gpf":"","related":["PROM-ADD-e8bf55cb"],"last":1613887902168,"eval":null,"time":141821,"unit":"","t_comfort":"","t_eco":"","t_nofrost":"","t_cool":"","t_hysteresis":"","store":"","lastValue":"0","change":-1,"unitValue":"1"},{"id":"KOLED1","device":"HQP","address":"0H.2","haddr":"PROM-HQP-O-0H.2","parent":"0H","name":"Ledy na suficie dark","value":"0","timeout":"180","type":"S","io":"o","active":"1","_updated":1613886686184,"gpf":"","last":1613886686184,"eval":null,"time":648861,"lastValue":"0","change":-1,"unitValue":"1"},{"id":"4","device":"HQP","address":"0K.7","haddr":"PROM-HQP-O-0K.7","parent":"0K","name":"Światło kotłownia","value":"0","timeout":"0","type":"S","io":"o","active":"1","_updated":1613835774384,"related":["PROM-ADD-164372de"],"last":1613835774384,"eval":null,"time":27935,"unit":"","store":"","t_comfort":"","t_eco":"","t_nofrost":"","t_cool":"","t_hysteresis":"","lastValue":"1","change":0},{"id":"10","device":"HQP","address":"0G.4","haddr":"PROM-HQP-O-0G.4","parent":"0G","name":"Światło kuchnia","value":"0","timeout":"7200","type":"S","io":"o","active":"1","gpf":"","_updated":1613850085335,"related":["PROM-ADD-e8bf55cb"],"last":1613850085335,"eval":null,"time":16471,"lastValue":"1","change":-1,"unitValue":"1","unit":"","sh_type":"LIGHT","sh_traits":"OnOff","sh_nicks":"kitchen light","t_comfort":"","t_eco":"","t_nofrost":"","t_cool":"","t_hysteresis":"","store":"","t_rel":null},{"id":"KORLED","device":"HQP","address":"0H.1","haddr":"PROM-HQP-O-0H.1","parent":"0H","name":"Ledy na suficie","value":"0","timeout":"120","type":"S","io":"o","active":"1","_updated":1613886687184,"gpf":"","last":1613886687184,"eval":null,"time":61039,"lastValue":"1","change":0,"unitValue":"0"},{"id":"96","device":"HQP","address":"0H.9","haddr":"PROM-HQP-I-0H.9","parent":"0H","name":"Salon przycisk roleta lewa","value":"0","type":"1","io":"i","active":"1","gpf":"","_updated":1613833610588,"last":1613833610588,"time":550675312,"eval":null,"lastValue":"1","change":0},{"id":"66","device":"HQP","address":"0L.6","haddr":"PROM-HQP-I-0L.6","parent":"0L","name":"Piętro Seba przycisk BRĄZ","value":"1","type":"1","io":"i","active":"1","last":1613843687364,"time":3362144,"_updated":1613843687364,"gpf":"","eval":null,"lastValue":"0","change":0},{"id":"130","device":"HQP","address":"0L.14","haddr":"PROM-HQP-I-0L.14","parent":"0L","name":"Piętro przy balkonie PRAWY BRĄZ (L)","value":"","type":"1","io":"i","active":false,"_updated":1466664359962},{"id":"57","device":"HQP","address":"0L.11","haddr":"PROM-HQP-I-0L.11","parent":"0L","name":"Piętro przy balkonie PRAWY NIEB (P)","value":"","type":"1","io":"i","active":false,"_updated":1466664369494},{"id":"54","device":"HQP","address":"0G.6","haddr":"PROM-HQP-I-0G.6","parent":"0G","name":"Wiatrołap góra przycisk lewy","value":"1","type":"1","io":"i","active":"1","gpf":"","_updated":1609517265697,"last":1609517265697,"eval":null,"lastValue":"0","time":3653296,"change":0,"unit":"","sh_type":"","sh_traits":"","sh_nicks":"","t_comfort":"","t_eco":"","t_nofrost":"","t_cool":"","t_hysteresis":"","store":"","related":null,"t_rel":null},{"id":"93","device":"HQP","address":"0G.13","haddr":"PROM-HQP-I-0G.13","parent":"0G","name":"Parter kinkiet do piwnicy BRĄZ","value":"","type":"1","io":"i","active":"1"},{"id":"59","device":"HQP","address":"0L.7","haddr":"PROM-HQP-I-0L.7","parent":"0L","name":"Piętro łazienka BRĄZ - lewy","value":"1","type":"1","io":"i","active":true,"last":1613833635896,"time":549932055,"_updated":1613833635896,"gpf":"","eval":null,"lastValue":"0","change":0},{"id":"91","device":"HQP","address":"0H.2","haddr":"PROM-HQP-I-0H.2","parent":"0H","name":"Parter roleta do piwnicy lewy","value":"1","type":"1","io":"i","active":"1","last":1612767497157,"time":3639,"_updated":1612767497157,"eval":null,"lastValue":"0","change":0},{"id":"90","device":"HQP","address":"0H.1","haddr":"PROM-HQP-I-0H.1","parent":"0H","name":"Parter roleta do piwnicy prawy","value":"1","type":"1","io":"i","active":"1","last":1611513839901,"time":1996575328,"_updated":1611513839901,"eval":null,"lastValue":"0","change":0},{"id":"106","device":"HQP","address":"0H.10","haddr":"PROM-HQP-I-0H.10","parent":"0H","name":"Sypialnia roleta prawa przycisk","value":"0","type":"1","io":"i","active":"1","last":1608730628754,"time":48745,"_updated":1608730628754,"gpf":"","eval":null,"lastValue":"1","unit":"","t_comfort":"","t_eco":"","t_nofrost":"","t_cool":"","t_hysteresis":"","store":"","related":null,"t_rel":null,"change":0,"sh_type":"","sh_traits":"","sh_nicks":""},{"id":"72","device":"HQP","address":"0H.3","haddr":"PROM-HQP-I-0H.3","parent":"0H","name":"Parter łazienka okno NIEB włącznik prawy","value":"0","type":"1","io":"i","active":"1","last":1613833869608,"time":894417981,"_updated":1613833869609,"gpf":"","eval":null,"unit":"","t_comfort":"","t_eco":"","t_nofrost":"","t_cool":"","t_hysteresis":"","store":"","related":null,"lastValue":"1","change":0,"sh_type":"","sh_traits":"","sh_nicks":"","t_rel":null},{"id":"95","device":"HQP","address":"0H.15","haddr":"PROM-HQP-I-0H.15","parent":"0H","name":"Korytarz roleta przycisk","value":"0","type":"1","io":"i","active":"1","gpf":"","_updated":1613833916187,"last":1613833916187,"time":551046610,"eval":null,"lastValue":"1","change":0},{"id":"102","device":"HQP","address":"0J.5","haddr":"PROM-HQP-I-0J.5","parent":"0J","name":"Salon przycisk okno prawe NIEB prawe","value":"0","type":"1","io":"i","active":"1","gpf":"","_updated":1609444070719,"last":1609444070719,"time":770806,"eval":null,"lastValue":"1","change":0},{"id":"100","device":"HQP","address":"0H.8","haddr":"PROM-HQP-I-0H.8","parent":"0H","name":"Parter rolety schody prawy","value":"1","type":"1","io":"i","active":"1","last":1609515315362,"time":1044,"_updated":1609515315362,"eval":null,"lastValue":"0","change":0},{"id":"58","device":"HQP","address":"0L.0","haddr":"PROM-HQP-I-0L.0","parent":"0L","name":"Piętro łazienka NIEB - prawy","value":"0","type":"1","io":"i","active":"1","last":1613833635107,"time":766,"_updated":1613833635107,"gpf":"","eval":null,"lastValue":"1","change":0},{"id":"99","device":"HQP","address":"0H.7","haddr":"PROM-HQP-I-0H.7","parent":"0H","name":"Parter rolety schody lewy","value":"0","type":"1","io":"i","active":"1","last":1609515316566,"time":278,"_updated":1609515316566,"eval":null,"lastValue":"1","change":0},{"id":"36","device":"HQP","address":"0G.0","haddr":"PROM-HQP-I-0G.0","parent":"0G","name":"Parter gabinet roleta prawy przycisk","value":"1","type":"1","io":"i","active":"1","gpf":"","_updated":1613833922512,"last":1613833922512,"time":551021877,"eval":null,"lastValue":"0","change":0,"unit":"","sh_type":"","sh_traits":"","sh_nicks":"","t_comfort":"","t_eco":"","t_nofrost":"","t_cool":"","t_hysteresis":"","store":"","related":null,"t_rel":null},{"id":"89","device":"HQP","address":"0H.5","haddr":"PROM-HQP-I-0H.5","parent":"0H","name":"Parter gabinet roleta lewo","value":"0","type":"1","io":"i","active":"1","last":1613833922144,"time":551024005,"_updated":1613833922144,"gpf":"","eval":null,"lastValue":"1","change":0,"unit":"","sh_type":"","sh_traits":"","sh_nicks":"","t_comfort":"","t_eco":"","t_nofrost":"","t_cool":"","t_hysteresis":"","store":"","related":null,"t_rel":null},{"id":"62","device":"HQP","address":"0L.2","haddr":"PROM-HQP-I-0L.2","parent":"0L","name":"Piętro Marcin NIEB","value":"0","type":"1","io":"i","active":"1","last":1613849081148,"time":4149544,"_updated":1613849081149,"gpf":"","eval":null,"lastValue":"1","change":0,"unit":"","sh_type":"","sh_traits":"","sh_nicks":"","t_comfort":"","t_eco":"","t_nofrost":"","t_cool":"","t_hysteresis":"","store":"","related":null,"t_rel":null},{"id":"63","device":"HQP","address":"0L.1","haddr":"PROM-HQP-I-0L.1","parent":"0L","name":"Piętro Marcin BRĄZ","value":"0","type":"1","io":"i","active":"1","last":1613849081658,"time":4149664,"_updated":1613849081658,"gpf":"","eval":null,"lastValue":"1","change":0,"unit":"","sh_type":"","sh_traits":"","sh_nicks":"","t_comfort":"","t_eco":"","t_nofrost":"","t_cool":"","t_hysteresis":"","store":"","related":null,"t_rel":null},{"id":"67","device":"HQP","address":"0L.12","haddr":"PROM-HQP-I-0L.12","parent":"0L","name":"Piętro korytarz antresola NIEB","value":"0","type":"1","io":"i","active":"1","gpf":"","_updated":1613246979933,"last":1613246979933,"time":5662795,"eval":null,"lastValue":"1","change":0},{"id":"60","device":"HQP","address":"0L.13","haddr":"PROM-HQP-I-0L.13","parent":"0L","name":"Piętro przy wyjściu na taras LEWY","value":"0","type":"1","io":"i","active":"1","gpf":"","_updated":1613833658624,"last":1613833658624,"time":550039843,"eval":null,"lastValue":"1","change":0},{"id":"103","device":"HQP","address":"0J.8","haddr":"PROM-HQP-I-0J.8","parent":"0J","name":"Salon przycisk okno prawe BRĄZ lewe","value":"0","type":"1","io":"i","active":"1","gpf":"","_updated":1605798690239,"last":1605798690239,"time":2510,"eval":null,"lastValue":"1","change":0},{"id":"108","device":"HQP","address":"0H.0","haddr":"PROM-HQP-I-0H.0","parent":"0H","name":"Przycisk roleta Janusza","value":"1","type":"1","io":"i","active":"1","gpf":"","_updated":1613833793777,"last":1613833793777,"eval":null,"time":551077705,"lastValue":"0","change":0,"unit":"","sh_type":"","sh_traits":"","sh_nicks":"","t_comfort":"","t_eco":"","t_nofrost":"","t_cool":"","t_hysteresis":"","store":"","related":null,"t_rel":null},{"id":"92","device":"HQP","address":"0G.12","haddr":"PROM-HQP-I-0G.12","parent":"0G","name":"Parter włącznik zejście do piwnicy","value":"0","type":"1","io":"i","active":"1","last":1613850053512,"time":861495,"_updated":1613850053513,"gpf":"","eval":null,"lastValue":"1","change":-1,"unitValue":"1"},{"id":"104","device":"HQP","address":"0H.14","haddr":"PROM-HQP-I-0H.14","parent":"0H","name":"Salon przycisk witraż NIEB","value":"0","type":"0","io":"i","active":"1","gpf":"","_updated":1612989641827,"last":1612989641826,"time":153,"eval":null,"store":"","related":null,"lastValue":"1","change":0},{"id":"77","device":"HQP","address":"0G.15","haddr":"PROM-HQP-I-0G.15","parent":"0G","name":"Salon przycisk BRĄZ prawy","value":"0","type":"0","io":"i","active":"1","gpf":"","_updated":1613847962675,"last":1613847962675,"time":283,"eval":null,"store":"","related":null,"unit":"","t_comfort":"","t_eco":"","t_nofrost":"","t_cool":"","t_hysteresis":"","lastValue":"1","change":-1,"unitValue":"1"},{"id":"PA0J15","device":"HQP","address":"0J.15","haddr":"PROM-HQP-I-0J.15","parent":"0J","name":"Łazienka dół - mały pstryczek włącznik","value":"1","type":"1","io":"i","active":"1","gpf":"","_updated":1573136701303,"last":1573136701303,"time":166,"eval":null,"lastValue":"0","change":0,"unit":"","sh_type":"","sh_traits":"","sh_nicks":"","t_comfort":"","t_eco":"","t_nofrost":"","t_cool":"","t_hysteresis":"","store":"","related":null,"t_rel":null},{"id":"75","device":"HQP","address":"0J.3","haddr":"PROM-HQP-I-0J.3","parent":"0J","name":"Sypialnia przycisk drzwi","value":"0","type":"1","io":"i","active":"1","last":1613853593143,"time":3490738,"_updated":1613853593143,"gpf":"","eval":null,"lastValue":"1","change":0,"unit":"","t_comfort":"","t_eco":"","t_nofrost":"","t_cool":"","t_hysteresis":"","store":"","related":null,"t_rel":null,"sh_type":"","sh_traits":"","sh_nicks":""},{"id":"CCW","device":"HQP","address":"0K.6","haddr":"PROM-HQP-I-0K.6","parent":"0K","name":"Czujnik ciepłej wody nieużywany","value":"0","type":"","io":"i","active":"1","gpf":"","_updated":1545047597593,"last":1542359901210,"time":26741235111,"eval":"","lastValue":"1","unit":"","t_comfort":"","t_eco":"","t_nofrost":"","t_cool":"","t_hysteresis":"","store":"","related":null,"t_rel":null},{"id":"115","device":"HQP","address":"0O.0","haddr":"PROM-HQP-I-0O.0","parent":"0O","name":"Parter gabinet przycisk","value":"0","type":"1","io":"i","active":"1","last":1613850631087,"time":1552317,"_updated":1613850631087,"gpf":"","eval":null,"lastValue":"1","change":0,"unit":"","sh_type":"","sh_traits":"","sh_nicks":"","t_comfort":"","t_eco":"","t_nofrost":"","t_cool":"","t_hysteresis":"","store":"","related":null,"t_rel":null},{"id":"76","device":"HQP","address":"0G.14","haddr":"PROM-HQP-I-0G.14","parent":"0G","name":"Salon przycisk NIEB lewy","value":"0","type":"0","io":"i","active":"1","gpf":"","_updated":1613847961942,"last":1613847961942,"time":282,"eval":null,"store":"","related":null,"unit":"","t_comfort":"","t_eco":"","t_nofrost":"","t_cool":"","t_hysteresis":"","lastValue":"1","change":0},{"id":"88","device":"HQP","address":"0J.7","haddr":"PROM-HQP-I-0J.7","parent":"0J","name":"Korytarz parter przycisk przy sypialni ","value":"0","type":"","io":"i","active":"1","gpf":"","_updated":1613858477349,"last":1613858477349,"time":126,"eval":null,"store":"","related":null,"lastValue":"1","change":0,"unit":"","sh_type":"","sh_traits":"","sh_nicks":"","t_comfort":"","t_eco":"","t_nofrost":"","t_cool":"","t_hysteresis":"","t_rel":null},{"id":"55","device":"HQP","address":"0G.1","haddr":"PROM-HQP-I-0G.1","parent":"0G","name":"Parter, korytarz przy wejściu","value":"0","type":"0","io":"i","active":"1","last":1613858468868,"time":233,"_updated":1613858468869,"eval":null,"store":"","related":null,"lastValue":"1","change":0},{"id":"56","device":"HQP","address":"0G.3","haddr":"PROM-HQP-I-0G.3","parent":"0G","name":"Parter łazienka włącznik","value":"0","type":"1","io":"i","active":"1","last":1613887247419,"time":78713,"_updated":1613887247419,"gpf":"","eval":null,"lastValue":"1","change":-1,"unitValue":"1","unit":"","sh_type":"","sh_traits":"","sh_nicks":"","t_comfort":"","t_eco":"","t_nofrost":"","t_cool":"","t_hysteresis":"","store":"","related":null,"t_rel":null},{"id":"84","device":"HQP","address":"0G.7","haddr":"PROM-HQP-I-0G.7","parent":"0G","name":"Piwnica schody","value":"1","type":"1","io":"i","active":"1","last":1613243382949,"time":1133946991,"_updated":1613243382950,"gpf":"","eval":null,"lastValue":"0","change":0},{"id":"81","device":"HQP","address":"0G.11","haddr":"PROM-HQP-I-0G.11","parent":"0G","name":"Parter schody BRĄZ - lewy","value":"0","type":"1","io":"i","active":"1","last":1613845646414,"time":778163,"_updated":1613845646414,"eval":null,"lastValue":"1","change":0},{"id":"70","device":"HQP","address":"0L.3","haddr":"PROM-HQP-I-0L.3","parent":"0L","name":"Piętro korytarz schody BRĄZ","value":"0","type":"1","io":"i","active":"1","gpf":"","_updated":1613848004811,"last":1613848004811,"time":3075934,"eval":null,"lastValue":"1","change":0},{"id":"82","device":"HQP","address":"0G.8","haddr":"PROM-HQP-I-0G.8","parent":"0G","name":"Piętro schody NIEB - lewy","value":"0","type":"1","io":"i","active":"1","gpf":"","_updated":1613242814979,"last":1613242814979,"time":256200985,"eval":null,"lastValue":"1","change":0},{"id":"69","device":"HQP","address":"0L.8","haddr":"PROM-HQP-I-0L.8","parent":"0L","name":"Piętro pokój Tomka prawe BRĄZ","value":"1","type":"1","io":"i","active":"1","last":1613848392023,"time":7875,"_updated":1613848392023,"eval":null,"lastValue":"0","unit":"","t_comfort":"","t_eco":"","t_nofrost":"","t_cool":"","t_hysteresis":"","store":"","related":null,"change":0},{"id":"65","device":"HQP","address":"0L.5","haddr":"PROM-HQP-I-0L.5","parent":"0L","name":"Piętro Seba przycisk NIEB","value":"0","type":"1","io":"i","active":"1","last":1613843686556,"time":3360596,"_updated":1613843686556,"gpf":"","eval":null,"lastValue":"1","change":0},{"id":"98","device":"HQP","address":"0I.0","haddr":"PROM-HQP-I-0I.0","parent":"0I","name":"Piętro korytarz antresola BRĄZ","value":"0","type":"1","io":"i","active":"1","gpf":"","_updated":1613241316488,"last":1613241316488,"time":746,"eval":null,"lastValue":"1","change":0},{"id":"113","device":"HQP","address":"0K.15","haddr":"PROM-HQP-I-0K.15","parent":"0K","name":"Alarm - czuwanie","value":"0","type":"","io":"i","active":"1","gpf":"","_updated":1595183005285,"last":1595183005285,"time":45019610,"eval":null,"lastValue":"1","_alias":"alarm","unit":"","t_comfort":"","t_eco":"","t_nofrost":"","t_cool":"","t_hysteresis":"","store":"","related":null,"change":0},{"id":"148","device":"HQP","address":"0K.8","haddr":"PROM-HQP-I-0K.8","parent":"0K","name":"Otwieranie furtki domofonem","value":"0","type":"1","io":"i","active":"1","last":1612956557307,"time":334922696,"_updated":1612956557307,"gpf":"","eval":null,"lastValue":"1","change":0},{"id":"64","device":"HQP","address":"0L.4","haddr":"PROM-HQP-I-0L.4","parent":"0L","name":"Piętro korytarz schody NIEB","value":"1","type":"1","io":"i","active":"1","last":1613849084255,"time":429,"_updated":1613849084255,"eval":null,"lastValue":"0","change":0},{"id":"61","device":"HQP","address":"0L.10","haddr":"PROM-HQP-I-0L.10","parent":"0L","name":"Piętro korytarz łazienka","value":"0","type":"1","io":"i","active":"1","last":1613848001836,"time":26214,"_updated":1613848001836,"eval":null,"lastValue":"1","change":1,"unitValue":"0"},{"id":"68","device":"HQP","address":"0L.9","haddr":"PROM-HQP-I-0L.9","parent":"0L","name":"Piętro pokój Tomka lewe NIEB","value":"0","type":"1","io":"i","active":"1","last":1613848367965,"time":1219,"_updated":1613848367965,"eval":null,"lastValue":"1","unit":"","t_comfort":"","t_eco":"","t_nofrost":"","t_cool":"","t_hysteresis":"","store":"","related":null,"change":0},{"id":"80","device":"HQP","address":"0G.10","haddr":"PROM-HQP-I-0G.10","parent":"0G","name":"Parter schody NIEB - prawy","value":"1","type":"1","io":"i","active":"1","last":1613845647043,"time":778345,"_updated":1613845647044,"eval":null,"lastValue":"0","change":0},{"id":"116","device":"HQP","address":"0K.12","haddr":"PROM-HQP-I-0K.12","parent":"0K","name":"Alarm - czujka piętro","value":"1","type":"1","io":"i","active":"1","gpf":"","_updated":1613863546943,"last":1613863546942,"time":65643,"eval":null,"lastValue":"0","change":0,"unit":"","sh_type":"","sh_traits":"","sh_nicks":"","t_comfort":"","t_eco":"","t_nofrost":"","t_cool":"","t_hysteresis":"","store":"","related":null,"t_rel":null},{"id":"85","device":"HQP","address":"0L.15","haddr":"PROM-HQP-I-0L.15","parent":"0L","name":"Piętro garderoba","value":"1","type":"0","io":"i","active":"1","last":1613241563453,"time":555314908,"_updated":1613241563453,"eval":null,"lastValue":"0","change":1,"unitValue":"0"},{"id":"73","device":"HQP","address":"0H.4","haddr":"PROM-HQP-I-0H.4","parent":"0H","name":"Parter łazienka okno BRĄZ włącznik lewy","value":"0","type":"1","io":"i","active":"1","last":1613245877753,"time":16548707,"_updated":1613245877753,"gpf":"","eval":null,"lastValue":"1","change":0,"unit":"","sh_type":"","sh_traits":"","sh_nicks":"","t_comfort":"","t_eco":"","t_nofrost":"","t_cool":"","t_hysteresis":"","store":"","related":null,"t_rel":null},{"id":"107","device":"HQP","address":"0H.12","haddr":"PROM-HQP-I-0H.12","parent":"0H","name":"Sypialnia roleta lewa przycisk","value":"0","type":"1","io":"i","active":"1","gpf":"","_updated":1609519816188,"last":1609519816188,"eval":null,"time":1882,"lastValue":"1","unit":"","t_comfort":"","t_eco":"","t_nofrost":"","t_cool":"","t_hysteresis":"","store":"","related":null,"t_rel":null,"change":0,"sh_type":"","sh_traits":"","sh_nicks":""},{"id":"144","device":"HQP","address":"0K.10","haddr":"PROM-HQP-I-0K.10","parent":"0K","name":"Studnia - pływak - nieużywany","value":"","type":"","io":"i","active":"1","unit":"","eval":"","t_comfort":"","t_eco":"","t_nofrost":"","t_cool":"","t_hysteresis":"","store":"","related":null,"t_rel":null,"_updated":1545047675667},{"id":"147","device":"HQP","address":"0K.11","haddr":"PROM-HQP-I-0K.11","parent":"0K","name":"Alarm - ALARM","value":"0","type":"0","io":"i","active":"1","gpf":"[gpf]","_updated":1613796878361,"last":1613796878360,"eval":null,"time":299894,"lastValue":"1","_alias":"alarmalarm","change":0},{"id":"87","device":"HQP","address":"0J.6","haddr":"PROM-HQP-I-0J.6","parent":"0J","name":"Wiatrołap dół przycisk","value":"0","type":"1","io":"i","active":"1","gpf":"","_updated":1613841638310,"eval":null,"store":"","related":null,"last":1613841638310,"time":7552443,"lastValue":"1","change":0,"unit":"","sh_type":"","sh_traits":"","sh_nicks":"","t_comfort":"","t_eco":"","t_nofrost":"","t_cool":"","t_hysteresis":"","t_rel":null},{"id":"94","device":"HQP","address":"0H.6","haddr":"PROM-HQP-I-0H.6","parent":"0H","name":"Przycisk kuchnia roleta","value":"0","type":"1","io":"i","active":"1","gpf":"","_updated":1613833588306,"last":1613833588306,"time":550105624,"eval":null,"lastValue":"1","change":0},{"id":"101","device":"HQP","address":"0H.13","haddr":"PROM-HQP-I-0H.13","parent":"0H","name":"Salon przycisk okno prawe od kominka","value":"0","type":"1","io":"i","active":"1","gpf":"","_updated":1613833350521,"last":1613833350521,"time":550701107,"eval":null,"lastValue":"1","change":0},{"id":"105","device":"HQP","address":"0H.11","haddr":"PROM-HQP-I-0H.11","parent":"0H","name":"Sypialnia przycisk taras","value":"1","type":"1","io":"i","active":"1","last":1613850119730,"time":16212622,"_updated":1613850119730,"gpf":"","eval":null,"lastValue":"0","change":0,"unit":"","t_comfort":"","t_eco":"","t_nofrost":"","t_cool":"","t_hysteresis":"","store":"","related":null,"t_rel":null,"sh_type":"","sh_traits":"","sh_nicks":""},{"id":"83","device":"HQP","address":"0G.9","haddr":"PROM-HQP-I-0G.9","parent":"0G","name":"Piętro schody BRĄZ - prawy","value":"0","type":"1","io":"i","active":"1","gpf":"","_updated":1613242816221,"last":1613242816221,"time":256201919,"eval":null,"lastValue":"1","change":0},{"id":"71","device":"HQP","address":"0G.4","haddr":"PROM-HQP-I-0G.4","parent":"0G","name":"Przycisk światło Janusza","value":"0","type":"1","io":"i","active":"1","gpf":"","_updated":1613848103099,"last":1613848103099,"time":3287,"eval":null,"lastValue":"1","change":0,"unit":"","sh_type":"","sh_traits":"","sh_nicks":"","t_comfort":"","t_eco":"","t_nofrost":"","t_cool":"","t_hysteresis":"","store":"","related":null,"t_rel":null},{"id":"109","device":"HQP","address":"0J.0","haddr":"PROM-HQP-I-0J.0","parent":"0J","name":"Parter garderoba","value":"1","type":"0","io":"i","active":"1","last":1613847815643,"time":24254,"_updated":1613847815643,"eval":null,"lastValue":"0","change":0},{"id":"78","device":"HQP","address":"0J.4","haddr":"PROM-HQP-I-0J.4","parent":"0J","name":"Przycisk kuchnia światło","value":"0","type":"1","io":"i","active":"1","gpf":"","_updated":1613850085297,"last":1613850085297,"time":16471,"eval":null,"unit":"","t_comfort":"","t_eco":"","t_nofrost":"","t_cool":"","t_hysteresis":"","store":"","related":null,"lastValue":"1","change":-1,"unitValue":"1"},{"id":"51","device":"HQP","address":"0K.3","haddr":"PROM-HQP-I-0K.3","parent":"0K","name":"Bilard prawy włącznik","value":"0","type":"","io":"i","active":"1","last":1613887641906,"time":170,"_updated":1613887641906,"gpf":"","eval":null,"unit":"","store":"","t_comfort":"","t_eco":"","t_nofrost":"","t_cool":"","t_hysteresis":"","related":null,"lastValue":"1","change":-1,"unitValue":"1","sh_type":"","sh_traits":"","sh_nicks":"","t_rel":null},{"id":"114","device":"HQP","address":"0K.14","haddr":"PROM-HQP-I-0K.14","parent":"0K","name":"Alarm - wszystkie czujki","value":"0","type":"","io":"i","active":"1","last":1613887854318,"time":29991,"_updated":1613887854318,"gpf":"","eval":null,"store":"","related":null,"unit":"","t_comfort":"","t_eco":"","t_nofrost":"","t_cool":"","t_hysteresis":"","lastValue":"1","change":-1,"unitValue":"1","sh_type":"","sh_traits":"","sh_nicks":"","t_rel":null},{"id":"49","device":"HQP","address":"0K.2","haddr":"PROM-HQP-I-0K.2","parent":"0K","name":"Piwnica kotłownia kontaktron","value":"1","type":"0","io":"i","active":"1","last":1613835774344,"time":27950,"_updated":1613835774345,"eval":null,"lastValue":"0","change":0},{"id":"79","device":"HQP","address":"0J.2","haddr":"PROM-HQP-I-0J.2","parent":"0J","name":"Spiżarnia kontaktron","value":"0","type":"0","io":"i","active":"1","gpf":"","_updated":1613887902130,"last":1613887902130,"time":141821,"eval":null,"lastValue":"1","change":1,"unitValue":"0"},{"id":"48","device":"HQP","address":"0K.1","haddr":"PROM-HQP-I-0K.1","parent":"0K","name":"Bilard lewy włącznik","value":"0","type":"","io":"i","active":"1","last":1613887642378,"time":192,"_updated":1613887642378,"gpf":"","eval":null,"unit":"","store":"","t_comfort":"","t_eco":"","t_nofrost":"","t_cool":"","t_hysteresis":"","related":null,"lastValue":"1","change":0,"sh_type":"","sh_traits":"","sh_nicks":"","t_rel":null},{"id":"50","device":"HQP","address":"0K.0","haddr":"PROM-HQP-I-0K.0","parent":"0K","name":"Sauna włącznik","value":"1","type":"1","io":"i","active":"1","last":1613887636936,"time":306589,"_updated":1613887636936,"gpf":"","eval":null,"lastValue":"0","change":1,"unitValue":"0"},{"id":"53","device":"HQP","address":"0G.5","haddr":"PROM-HQP-I-0G.5","parent":"0G","name":"Wiatrołap góra przycisk prawy","value":"0","type":"1","io":"i","active":"1","gpf":"","_updated":1612099491111,"last":1612099491111,"time":209,"eval":null,"lastValue":"1","change":0,"unit":"","sh_type":"","sh_traits":"","sh_nicks":"","t_comfort":"","t_eco":"","t_nofrost":"","t_cool":"","t_hysteresis":"","store":"","related":null,"t_rel":null},{"id":"112","device":"HQP","address":"0K.13","haddr":"PROM-HQP-I-0K.13","parent":"0K","name":"Alarm - czujka w wiatrołapie","value":"0","type":"1","io":"i","active":true,"last":1613849190753,"time":721935,"_updated":1613849190753,"gpf":"","eval":null,"unit":"","t_comfort":"","t_eco":"","t_nofrost":"","t_cool":"","t_hysteresis":"","store":"","related":null,"lastValue":"1","change":1,"unitValue":"0","sh_type":"","sh_traits":"","sh_nicks":"","t_rel":null},{"id":"146","device":"HQP","address":"0K.9","haddr":"PROM-HQP-I-0K.9","parent":"0K","name":"Pobór prądu","value":0.69,"type":"1","io":"i","active":"1","last":1613887918050,"time":13062,"_updated":1613887918051,"eval":"Math.round(900000/time)/100","store":"power/300","related":null,"unit":"kilowat","t_comfort":"","t_eco":"","t_nofrost":"","t_cool":"","t_hysteresis":"","lastValue":0.68,"_alias":"power","change":1,"unitValue":"0.68 kilowat"},{"_updated":1613886753434,"_created":1466185489090,"haddr":"PROM-ADD-30ee88ee","io":"o","name":"Światło dzienne","type":"o","device":"VAR","address":"DAYLIGHT","gpf":"","active":true,"value":"1","eval":null,"last":1613886753434,"time":1100884,"lastValue":"0","_alias":"daylight","change":0,"unit":"","sh_type":"","sh_traits":"","sh_nicks":"","t_comfort":"","t_eco":"","t_nofrost":"","t_cool":"","t_hysteresis":"","store":"","related":null,"t_rel":null},{"_updated":1595183005286,"_created":1466185828506,"haddr":"PROM-ADD-82af7689","io":"o","name":"W domu są ludzie","type":"o","device":"VAR","address":"FULLHOUSE","gpf":"","active":true,"value":"1","last":1595183005286,"eval":null,"time":18704849032,"lastValue":"0","_alias":"fh","unit":"","t_comfort":"","t_eco":"","t_nofrost":"","t_cool":"","t_hysteresis":"","store":"","related":null,"change":0},{"_updated":1613856606730,"_created":1466187632213,"haddr":"PROM-ADD-2e0a5155","io":"o","active":true,"name":"Potrzeba grzania ciepłej wody","type":"o","device":"VAR","address":"HOTWATER","gpf":"","value":"0","last":1613856606729,"eval":null,"time":6126011,"unit":"","t_comfort":"","t_eco":"","t_nofrost":"","t_cool":"","t_hysteresis":"","store":"","related":null,"lastValue":"0","_alias":"hotwater","t_rel":null,"change":1,"unitValue":0},{"_updated":1613818833436,"_created":1466187856542,"haddr":"PROM-ADD-13ae9fd5","io":"o","name":"Wakacje","type":"o","device":"VAR","address":"VACATION","gpf":"","active":true,"value":"0","last":1613818833435,"eval":null,"time":68990892,"lastValue":"1","_alias":"vacation","change":0,"unit":"","t_comfort":"","t_eco":"","t_nofrost":"","t_cool":"","t_hysteresis":"","store":"","related":null,"t_rel":null},{"_updated":1613883630703,"_created":1466586759453,"haddr":"PROM-ADD-28ccb81c","io":"o","name":"Dzień","type":"v","device":"VAR","address":"DAY","gpf":"","value":"1","active":true,"eval":null,"last":1613883630703,"time":2995358,"lastValue":"0","change":0},{"_updated":1574149477650,"_created":1466588964445,"haddr":"PROM-ADD-a82dc5b5","io":"o","active":true,"name":"Nic nie robić","type":"X","device":"VAR","address":"STILL","gpf":"","value":"0","last":1574149477650,"eval":null,"time":21033527635,"lastValue":"0","_alias":"nic","change":0},{"_updated":1613843935578,"_created":1466659379838,"haddr":"PROM-ADD-e6d86e93","io":"o","active":true,"name":"Sezon grzewczy","type":"T","device":"VAR","address":"HEATING","gpf":"","value":1,"last":1613843935578,"eval":null,"time":60051,"unit":"","store":"","t_comfort":"","t_eco":"","t_nofrost":"","t_cool":"","t_hysteresis":"","related":null,"lastValue":1,"_alias":"winter","change":0},{"_updated":1536829353385,"_created":1468996156618,"haddr":"PROM-ADD-164372de","io":"o","active":true,"name":"Światła piwnica","type":"G","device":"GRP","address":"2","gpf":"","related":["PROM-HQP-O-0K.9","PROM-HQP-O-0K.8","PROM-HQP-O-0K.6","PROM-HQP-O-0K.7","PROM-ADD-03d4fb68"],"value":0,"last":1613887642225,"eval":"value<=1?Math.round(value*100):value","time":449,"lastValue":0,"_alias":"lights0","unit":"","t_comfort":"","t_eco":"","t_nofrost":"","t_cool":"","t_hysteresis":"","store":"","change":1,"unitValue":"0"},{"_updated":1543175962594,"_created":1468996390693,"haddr":"PROM-ADD-03d4fb68","io":"g","active":true,"name":"Wszystkie światła","type":"G","device":"GRP","address":"1","related":["PROM-ADD-164372de","PROM-ADD-e8bf55cb","PROM-ADD-4d4dc234"],"value":2.67,"eval":null,"last":1613887902172,"time":141822,"lastValue":2.67,"_alias":"lights","change":-1,"unitValue":"7.67"},{"_updated":1536829255545,"_created":1468996642714,"haddr":"PROM-ADD-e8bf55cb","io":"o","active":true,"name":"Światła parter","type":"G","device":"GRP","address":"3","related":["PROM-HQP-O-0J.5","PROM-HQP-O-0G.7","PROM-HQP-O-0J.3","PROM-HQP-O-0G.6","PROM-HQP-O-0G.0","PROM-HQP-O-0J.7","PROM-HQP-O-0J.1","PROM-HQP-O-0G.3","PROM-HQP-O-0G.1","PROM-HQP-O-0J.4","PROM-HQP-O-0G.8","PROM-HQP-O-0J.0","PROM-HQP-O-0G.4","PROM-ADD-03d4fb68"],"value":8,"eval":"value<=1?Math.round(value*100):value","store":"","last":1613887902170,"time":141822,"lastValue":0.08,"_alias":"lights1","unit":"","t_comfort":"","t_eco":"","t_nofrost":"","t_cool":"","t_hysteresis":"","change":-1,"unitValue":"23"},{"_updated":1539783630377,"_created":1468997010567,"haddr":"PROM-ADD-4d4dc234","io":"o","active":true,"name":"Światła piętro","type":"G","device":"GRP","address":"4","related":["PROM-HQP-O-0L.4","PROM-HQP-O-0J.2","PROM-HQP-O-0L.1","PROM-HQP-O-0I.7","PROM-HQP-O-0L.6","PROM-HQP-O-0I.5","PROM-HQP-O-0L.5","PROM-HQP-O-0L.0","PROM-HQP-O-0L.8","PROM-HQP-O-0L.3","PROM-HQP-O-0L.9","PROM-ADD-03d4fb68","PR.HQP.b47179fa"],"value":0,"eval":"value<=1?Math.round(value*100):value","store":"","last":1613850884329,"time":1800036,"lastValue":0,"_alias":"lights2","unit":"","t_comfort":"","t_eco":"","t_nofrost":"","t_cool":"","t_hysteresis":"","change":1,"unitValue":"0"},{"_updated":1601482829538,"_created":1471022758022,"haddr":"PROM-ADD-e236be5d","io":"o","active":true,"name":"piwnica.sh","type":"S","device":"SHL","address":"/homekameleon/piwnica.sh","eval":null,"store":"","unit":"","related":null,"value":"00:24:8c:a5:46:fc","last":1601482829537,"time":13138202173,"t_comfort":"","t_eco":"","t_nofrost":"","t_cool":"","t_hysteresis":"","lastValue":"00:24:8c:a5:46:fc","change":0},{"_updated":1542526689935,"_created":1471242113786,"haddr":"PROM-ADD-06a4b9ca","io":"o","active":true,"name":"Średnia temperatura","type":"G","device":"GRP","address":"1","related":["PROM-HQP-T-0O","WHK-5ccf7fc5ff7c-t28eef6681216026d","WHK-5ccf7fc5ff7c-t28ff208085160547","WHK-5ccf7fc5ff7c-t28ff1a688516052b","WHK-5ccf7fc5ff7c-t28ff653f85160577"],"eval":null,"store":"","unit":"°C⇆","value":18.82,"last":1613887894493,"time":60051,"t_comfort":"","t_eco":"","t_nofrost":"","t_cool":"","t_hysteresis":"","lastValue":18.82,"_alias":"t_avg","change":1,"unitValue":"18.82 °C↘"},{"_updated":1613887825375,"_created":1471945481459,"haddr":"PROM-ADD-26c05fd6","io":"o","name":"Rodzaj temperatur w domu","type":"T","device":"VAR","address":"temperature","unit":"typ","eval":null,"store":"","t_h_comfort":"","t_h_eco":"","t_h_nofrost":"","t_h_cool":"","t_h_hysteresis":"","related":null,"active":true,"value":"comfort","last":1613887825375,"time":109168,"lastValue":"comfort","change":0,"unitValue":"comfort","t_comfort":"","t_eco":"","t_nofrost":"","t_cool":"","t_hysteresis":"","t_rel":null,"_alias":"tkco"},{"_updated":1475392662926,"_created":1472070025723,"haddr":"PROM-ADD-59bc7b09","io":"o","active":true,"name":"ssh","type":"S","device":"SHL","address":"ssh","unit":"","eval":"","store":"","t_comfort":"","t_eco":"","t_nofrost":"","t_cool":"","t_hysteresis":"","related":null,"value":"pudel@192.168.0.12 touch /tmp/ala2","last":1472070371458,"time":1472070371458},{"_updated":1613887824329,"_created":1472897684437,"haddr":"PROM-ADD-ed1db10f","io":"o","active":true,"name":"Bezruch","type":"t","device":"VAR","address":"nomotion","unit":"","eval":"Math.round(time/1000)","store":"","t_comfort":"","t_eco":"","t_nofrost":"","t_cool":"","t_hysteresis":"","related":null,"value":109,"last":1613887824329,"time":109159,"lastValue":50,"_alias":"idle","change":1,"unitValue":84},{"_updated":1613887894526,"_created":1476707120535,"haddr":"WHK-5ccf7fc62df-o1","name":"Kaloryfer łazienka parter","device":"WHK","address":"5ccf7fc62df.o.1","io":"o","value":"1","active":true,"unit":"","last":1613887894526,"eval":null,"time":57094,"t_comfort":"","t_eco":"","t_nofrost":"","t_cool":"","t_hysteresis":"","store":"","related":["PR.GRP.1c758ac6"],"lastValue":"1","change":0,"unitValue":"0"},{"_updated":1613887894518,"_created":1476707120536,"haddr":"WHK-5ccf7fc62df-o2","name":"Kaloryfer Janusz","device":"WHK","address":"5ccf7fc62df.o.2","io":"o","value":"1","active":true,"unit":"","last":1613887894518,"eval":null,"time":60059,"t_comfort":"","t_eco":"","t_nofrost":"","t_cool":"","t_hysteresis":"","store":"","related":["PR.GRP.1c758ac6"],"lastValue":"1","change":1,"unitValue":"0","type":"","sh_type":"","sh_traits":"","sh_nicks":"","t_rel":null},{"_updated":1558676061599,"_created":1476707538824,"haddr":"WHK-5ccf7fc607e-o1","name":"gabinet nieużywany, kiedyś kaloryfer obok w pokoju","device":"WHK","address":"5ccf7fc607e.o.1","io":"o","value":"0","active":true,"unit":"","last":1548252832240,"eval":"","time":44237,"t_comfort":"","t_eco":"","t_nofrost":"","t_cool":"","t_hysteresis":"","store":"","related":[],"lastValue":"1","change":0,"unitValue":"0","type":"","t_rel":null,"sh_type":"","sh_traits":"","sh_nicks":""},{"_updated":1613887894519,"_created":1476707538825,"haddr":"WHK-5ccf7fc607e-o2","name":"Kaloryfer gabinet","device":"WHK","address":"5ccf7fc607e.o.2","io":"o","value":"1","active":true,"unit":"","last":1613887894519,"eval":null,"time":59059,"t_comfort":"","t_eco":"","t_nofrost":"","t_cool":"","t_hysteresis":"","store":"","related":["PR.GRP.1c758ac6"],"lastValue":"1","change":0,"unitValue":"0","type":"","sh_type":"","sh_traits":"","sh_nicks":"","t_rel":null},{"_updated":1613887902169,"_created":1478016486522,"active":true,"haddr":"PR.VAR.6db1187d","device":"VAR","io":"o","address":10,"name":"Ciemność w spiżarni przy otwartych drzwiach","unit":"","eval":null,"t_comfort":"","t_eco":"","t_nofrost":"","t_cool":"","t_hysteresis":"","store":"","related":null,"value":"0","last":1613887902169,"time":141821,"lastValue":"0","change":1,"unitValue":"0"},{"_updated":1610568209680,"_created":1484654016454,"haddr":"WHK-5ccf7fc3c3ed-o1","name":"niepodłączone w szafie","device":"WHK","address":"5ccf7fc3c3ed.o.1","io":"o","value":"0","active":true,"unit":"","eval":null,"t_comfort":"","t_eco":"","t_nofrost":"","t_cool":"","t_hysteresis":"","store":"","related":null,"last":1610568209679,"time":2195,"lastValue":"1","change":0},{"_updated":1513957303153,"_created":1484654016458,"haddr":"WHK-5ccf7fc3c3ed-o2","name":"zespute wyjście","device":"WHK","address":"5ccf7fc3c3ed.o.2","io":"o","value":"0","active":true,"unit":"","last":1513957172161,"eval":"","time":49461,"t_comfort":"","t_eco":"","t_nofrost":"","t_cool":"","t_hysteresis":"","store":"","related":null},{"_updated":1574177068217,"_created":1511179715149,"active":true,"haddr":"PR.HQP.353a25d2","device":"HQP","io":"o","address":"0P.5","name":"Reset kotła","unit":"","eval":null,"t_comfort":"","t_eco":"","t_nofrost":"","t_cool":"","t_hysteresis":"","store":"","related":null,"value":"0","last":1574177068217,"time":180063,"lastValue":"0","change":0},{"_updated":1537679975269,"_created":1513600201226,"haddr":"WHK-5ccf7fc5ff7c-o1","name":"zepsute","device":"WHK","address":"5ccf7fc5ff7c.o.1","io":"o","value":"0","active":true,"unit":"","last":1537679975268,"eval":null,"time":80,"related":null,"t_comfort":"","t_eco":"","t_nofrost":"","t_cool":"","t_hysteresis":"","store":"","lastValue":"0"},{"_updated":1535529550576,"_created":1513600201229,"haddr":"WHK-5ccf7fc5ff7c-o2","name":"zepsute","device":"WHK","address":"5ccf7fc5ff7c.o.2","io":"o","value":"0","active":true,"unit":"","last":1535529550573,"eval":null,"time":4182,"t_comfort":"","t_eco":"","t_nofrost":"","t_cool":"","t_hysteresis":"","store":"","related":null,"lastValue":"1"},{"_updated":1611474293756,"_created":1513600399322,"haddr":"WHK-5ccf7fc3fa1-o1","name":"Christmas - lampki choinkowe","device":"WHK","address":"5ccf7fc3fa1.o.1","io":"o","value":"0","active":true,"unit":"","last":1611474293756,"eval":null,"time":6245539,"related":["PR.GRP.64472e9c"],"t_comfort":"","t_eco":"","t_nofrost":"","t_cool":"","t_hysteresis":"","store":"","lastValue":"1","change":0,"type":"","t_rel":null},{"_updated":1535545432331,"_created":1513600399325,"haddr":"WHK-5ccf7fc3fa1-o2","name":"Też jakiś christmas ;)","device":"WHK","address":"5ccf7fc5ff7c.t.28ff1a688516052b","io":"t","value":"0","active":true,"unit":"°C","last":1513954920230,"eval":"","time":1327,"t_comfort":"","t_eco":"","t_nofrost":"","t_cool":"","t_hysteresis":"","store":"","related":null},{"_updated":1577353857566,"_created":1513613371868,"active":true,"haddr":"PR.GRP.64472e9c","device":"GRP","io":"o","address":8,"name":"Christmas","related":["WHK-5ccf7fc3fa1-o1","WHK-b4e62d30ab0-o2"],"value":0,"last":1613685038402,"eval":null,"time":56993682,"unit":"","t_comfort":"","t_eco":"","t_nofrost":"","t_cool":"","t_hysteresis":"","store":"","lastValue":0,"change":-1,"unitValue":"0.4","type":"","t_rel":null,"sh_type":"LIGHT","sh_traits":"OnOff","sh_nicks":"christmas,christmas tree"},{"_updated":1518797753195,"_created":1516365058769,"active":true,"haddr":"PR.GRP.ab52b4e6","device":"GRP","io":"o","address":9,"name":"Aktywność pieca","unit":"","related":["PROM-HQP-O-0P.4","PROM-HQP-O-0P.3"],"eval":null,"t_comfort":"","t_eco":"","t_nofrost":"","t_cool":"","t_hysteresis":"","store":"gaz/300","value":0.5,"last":1613884291394,"lastValue":0.5,"time":660546,"change":1,"unitValue":0.5},{"_updated":1613887486048,"_created":1531860786339,"haddr":"WHK-5ccf7fc3c3ed-t28ff76d48416046d","name":"Temperatura w łazience piętro","device":"WHK","address":"5ccf7fc3c3ed.t.28ff76d48416046d","io":"t","value":18.87,"active":true,"unit":"°C","last":1613887486048,"eval":null,"lastValue":18.87,"time":38998,"t_comfort":"20","t_eco":"19","t_nofrost":"15","t_cool":"30","t_hysteresis":"0.1","store":"temp_laz_pietr/300","related":["PR.GRP.84a59a80"],"temp_change":1,"change":-1,"unitValue":"18.87 °C","type":"","t_rel":null,"sh_type":"","sh_traits":"","sh_nicks":""},{"_updated":1613887483235,"_created":1531860786342,"haddr":"WHK-5ccf7fc3c3ed-t28ff1579851605f3","name":"Temperatura Tomek piętro","device":"WHK","address":"5ccf7fc3c3ed.t.28ff1579851605f3","io":"t","value":19.5,"active":true,"unit":"°C","eval":null,"t_comfort":"20.2","t_eco":"19","t_nofrost":"18","t_cool":"25","t_hysteresis":"0.15","store":"temp_long/300","related":["PR.GRP.84a59a80"],"last":1613887483235,"lastValue":19.43,"time":69211,"temp_change":1,"type":"","change":-1,"unitValue":"19.43 °C","t_rel":"PROM-ADD-26c05fd6","sh_type":"","sh_traits":"","sh_nicks":""},{"_updated":1613887450021,"_created":1535306720292,"haddr":"WHK-5ccf7fc3c3ed-t28fff55a851605d1","name":"Temperatura Marcin piętro","device":"WHK","address":"5ccf7fc3c3ed.t.28fff55a851605d1","io":"t","value":19.37,"active":true,"unit":"°C","eval":null,"t_comfort":"20.2","t_eco":"19","t_nofrost":"18","t_cool":"25","t_hysteresis":"0.1","store":"temp_gab/300","related":["PR.GRP.84a59a80"],"last":1613887450020,"lastValue":19.37,"time":45082,"temp_change":1,"change":-1,"unitValue":"19.37 °C","type":"","t_rel":"PROM-ADD-26c05fd6","sh_type":"","sh_traits":"","sh_nicks":""},{"_updated":1613887486038,"_created":1535307331890,"haddr":"WHK-5ccf7fc3c3ed-t28ff6e9f851605ae","name":"Temperatura Seba piętro","device":"WHK","address":"5ccf7fc3c3ed.t.28ff6e9f851605ae","io":"t","value":19.62,"active":true,"unit":"°C","last":1613887486038,"eval":null,"lastValue":19.62,"time":66048,"related":["PR.GRP.84a59a80"],"t_comfort":"20","t_eco":"19","t_nofrost":"18","t_cool":"25","t_hysteresis":"0.1","store":"temp_seb/300","temp_change":1,"change":-1,"unitValue":"19.62 °C","type":"","t_rel":"PROM-ADD-26c05fd6","sh_type":"","sh_traits":"","sh_nicks":""},{"_updated":1613886282040,"_created":1535368423837,"haddr":"WHK-b4e62d30ab0-o1","name":"Kaloryfer u Tomka","device":"WHK","address":"b4e62d30ab0.o.1","io":"o","value":"1","active":true,"unit":"","last":1613886282040,"eval":null,"lastValue":"1","time":68885,"related":["PR.GRP.1c758ac6"],"t_comfort":"","t_eco":"","t_nofrost":"","t_cool":"","t_hysteresis":"","store":"","change":0,"unitValue":"0"},{"_updated":1613685038401,"_created":1535368423841,"haddr":"WHK-b4e62d30ab0-o2","name":"Lamki z przodu domu","device":"WHK","address":"b4e62d30ab0.o.2","io":"o","value":"0","active":true,"unit":"","last":1613685038401,"eval":null,"lastValue":"1","time":56993682,"related":["PR.GRP.64472e9c"],"t_comfort":"","t_eco":"","t_nofrost":"","t_cool":"","t_hysteresis":"","store":"","change":-1,"unitValue":"1"},{"_updated":1613887486064,"_created":1535368740176,"haddr":"WHK-b4e62d30aaf1-o1","name":"Kaloryfer Seba","device":"WHK","address":"b4e62d30aaf1.o.1","io":"o","value":"1","active":true,"unit":"","last":1613887486064,"eval":null,"lastValue":"1","time":66059,"related":["PR.GRP.1c758ac6"],"t_comfort":"","t_eco":"","t_nofrost":"","t_cool":"","t_hysteresis":"","store":"","change":0,"unitValue":"0"},{"_updated":1613887450040,"_created":1535368740179,"haddr":"WHK-b4e62d30aaf1-o2","name":"Kaloryfer Marcin","device":"WHK","address":"b4e62d30aaf1.o.2","io":"o","value":"1","active":true,"unit":"","last":1613887450040,"eval":null,"lastValue":"1","time":45078,"t_comfort":"","t_eco":"","t_nofrost":"","t_cool":"","t_hysteresis":"","store":"","related":["PR.GRP.1c758ac6"],"change":0,"unitValue":"0"},{"_updated":1613887486084,"_created":1535459505961,"active":true,"haddr":"PROM-HQP-O-0I.4","parent":"0I","device":"HQP","io":"o","address":"0I.4","name":"Kaloryfer łazienka piętro","unit":"","eval":null,"t_comfort":"","t_eco":"","t_nofrost":"","t_cool":"","t_hysteresis":"","store":"","related":["PR.GRP.1c758ac6"],"value":"1","last":1613887486084,"lastValue":"1","time":38998,"change":0,"unitValue":"0"},{"_updated":1613887894465,"_created":1535488329524,"haddr":"WHK-5ccf7fc3fcd1-t28eeff5b151601c6","name":"Temperatura w piwnicy","device":"WHK","address":"5ccf7fc3fcd1.t.28eeff5b151601c6","io":"t","value":17.5,"active":true,"unit":"°C","last":1613887894465,"eval":null,"lastValue":17.5,"time":60052,"t_comfort":"16","t_eco":"16","t_nofrost":"10","t_cool":"25","t_hysteresis":"0.1","store":"temp_sau/300","related":null,"temp_change":-1,"_alias":"t_piw","change":1,"unitValue":"17.5 °C"},{"_updated":1613887894484,"_created":1535526659134,"haddr":"WHK-5ccf7fc3fcd1-t28ff167684160351","name":"Temperatura w zasobniku wody","device":"WHK","address":"5ccf7fc3fcd1.t.28ff167684160351","io":"t","value":40.06,"active":true,"unit":"°C⇆","last":1613887894484,"eval":null,"lastValue":40.37,"time":60059,"t_comfort":"60","t_eco":"41","t_nofrost":"6","t_cool":"100","t_hysteresis":"2","store":"temp_wody/300","related":null,"temp_change":-1,"_alias":"t_water","type":"","t_rel":"PR.VAR.7e379d9a","change":1,"unitValue":"40.37 °C↘"},{"_updated":1613887894487,"_created":1535526659149,"haddr":"WHK-5ccf7fc3fcd1-t28ffb7818516052e","name":"Temperatura powrotu do pieca","device":"WHK","address":"5ccf7fc3fcd1.t.28ffb7818516052e","io":"t","value":34.37,"active":true,"unit":"°C⇆","last":1613887894487,"eval":null,"lastValue":34.37,"time":60051,"t_comfort":"25","t_eco":"25","t_nofrost":"25","t_cool":"50","t_hysteresis":"0.2","store":"emp_piec_wy/300","related":null,"temp_change":-1,"_alias":"t_return","type":"","change":-1,"unitValue":"34.37 °C↗"},{"_updated":1613887894488,"_created":1535532149611,"haddr":"WHK-5ccf7fc5ff7c-t28eef6681216026d","name":"Temperatura u Janusza","device":"WHK","address":"5ccf7fc5ff7c.t.28eef6681216026d","io":"t","value":18.12,"active":true,"unit":"°C","last":1613887894488,"eval":null,"lastValue":18.18,"time":60051,"t_comfort":"19","t_eco":"17.8","t_nofrost":"16","t_cool":"28","t_hysteresis":"0.2","store":"temp_zab/300","related":["PROM-ADD-06a4b9ca"],"temp_change":1,"change":-1,"unitValue":"18.18 °C","type":"","t_rel":null,"sh_type":"","sh_traits":"","sh_nicks":""},{"_updated":1613887894475,"_created":1535532149612,"haddr":"WHK-5ccf7fc5ff7c-t282da52700008079","name":"Temperatura na zewnątrz","device":"WHK","address":"5ccf7fc5ff7c.t.282da52700008079","io":"t","value":0.5,"active":true,"unit":"°C⇆","last":1613887894475,"eval":null,"lastValue":0.5,"time":60047,"t_comfort":"","t_eco":"","t_nofrost":"","t_cool":"","t_hysteresis":"","store":"temp_zew/300","related":null,"_alias":"t_out","type":"","change":1,"unitValue":"0.5 °C↘","t_rel":null,"sh_type":"","sh_traits":"","sh_nicks":""},{"_updated":1613887894512,"_created":1535539208987,"haddr":"WHK-5ccf7fc5ff7c-t28ff208085160547","name":"Temperatura w łazience parter","device":"WHK","address":"5ccf7fc5ff7c.t.28ff208085160547","io":"t","value":19.43,"active":true,"unit":"°C","last":1613887894512,"eval":null,"lastValue":19.43,"time":57100,"t_comfort":"20","t_eco":"19","t_nofrost":"17","t_cool":"28","t_hysteresis":"0.15","store":"temp_laz_part/300","related":["PROM-ADD-06a4b9ca"],"temp_change":1,"change":-1,"unitValue":"19.43 °C","type":"","t_rel":null,"sh_type":"","sh_traits":"","sh_nicks":""},{"_updated":1613887894499,"_created":1535543641994,"haddr":"WHK-5ccf7fc5ff7c-t28ff1a688516052b","name":"Temperatura w salonie ","device":"WHK","address":"5ccf7fc5ff7c.t.28ff1a688516052b","io":"t","value":19.25,"active":true,"unit":"°C","last":1613887894499,"eval":null,"lastValue":19.25,"time":31,"t_comfort":"20.2","t_eco":"19","t_nofrost":"17","t_cool":"30","t_hysteresis":"-0.2","store":"temp_sal/300","related":["PROM-ADD-06a4b9ca"],"temp_change":1,"change":-1,"unitValue":"19.25 °C","type":"","t_rel":"PROM-ADD-26c05fd6","sh_type":"","sh_traits":"","sh_nicks":""},{"_updated":1613887894521,"_created":1535543641997,"haddr":"WHK-5ccf7fc5ff7c-t28ff653f85160577","name":"Temperatura sypialnia ","device":"WHK","address":"5ccf7fc5ff7c.t.28ff653f85160577","io":"t","value":17.62,"active":true,"unit":"°C","last":1613887894520,"eval":null,"lastValue":17.62,"time":57096,"t_comfort":"19.6","t_eco":"17.5","t_nofrost":"17.2","t_cool":"28","t_hysteresis":"0.3","store":"temp_sch/300","related":["PROM-ADD-06a4b9ca"],"temp_change":1,"change":-1,"unitValue":"17.62 °C","type":"","t_rel":null,"sh_type":"","sh_traits":"","sh_nicks":""},{"_updated":1613883630703,"_created":1535603878718,"active":true,"haddr":"PR.VAR.f0bd06aa","device":"VAR","io":"o","address":"tod","name":"Pora dnia","unit":"","eval":null,"t_comfort":"","t_eco":"","t_nofrost":"","t_cool":"","t_hysteresis":"","store":"","related":null,"value":"m","last":1613883630703,"lastValue":"n","time":4263773,"change":0,"type":"","sh_type":"","sh_traits":"","sh_nicks":"","t_rel":null},{"_updated":1613883635809,"_created":1536067460319,"active":true,"haddr":"PR.SHL.a1e1fa6c","device":"SHL","io":"o","address":"/homekameleon/fsync.sh","name":"fsync.sh","unit":"","eval":null,"t_comfort":"","t_eco":"","t_nofrost":"","t_cool":"","t_hysteresis":"","store":"","related":null,"value":"1","last":1613883635809,"lastValue":"1","time":25822911,"change":0},{"_updated":1570449849474,"_created":1536815583420,"active":true,"haddr":"PR.GRP.1c758ac6","device":"GRP","io":"o","address":10,"name":"Kaloryfery","unit":"","related":["PROM-HQP-O-0K.5","PROM-HQP-O-0J.6","WHK-5ccf7fc62df-o1","WHK-5ccf7fc62df-o2","WHK-5ccf7fc607e-o2","WHK-b4e62d30ab0-o1","WHK-b4e62d30aaf1-o1","WHK-b4e62d30aaf1-o2","PROM-HQP-O-0I.4","WHK-5ccf7fc3fcf4-o1"],"eval":"value<=1?Math.round(value*100):value","t_comfort":"","t_eco":"","t_nofrost":"","t_cool":"","t_hysteresis":"","store":"","value":90,"last":1613885059938,"lastValue":0.9,"time":41,"_alias":"radiators","type":"","change":1,"unitValue":0,"sh_type":"","sh_traits":"","sh_nicks":"","t_rel":null},{"_updated":1536953511724,"_created":1536952355590,"active":true,"haddr":"PR.GRP.84a59a80","device":"GRP","io":"o","address":9,"name":"Średnia temperatura na piętrze","unit":"°C","related":["WHK-5ccf7fc3c3ed-t28ff76d48416046d","WHK-5ccf7fc3c3ed-t28ff1579851605f3","WHK-5ccf7fc3c3ed-t28fff55a851605d1","WHK-5ccf7fc3c3ed-t28ff6e9f851605ae"],"eval":null,"t_comfort":"","t_eco":"","t_nofrost":"","t_cool":"","t_hysteresis":"","store":"","_alias":"t_avg2","value":19.34,"last":1613887483244,"lastValue":19.34,"time":78293,"change":1,"unitValue":"19.34 °C"},{"_updated":1613849081695,"_created":1539718344135,"active":true,"haddr":"PR.HQP.d406e201","device":"HQP","io":"o","address":"0I.3","name":"Górne światło u Marcina","unit":"","eval":null,"type":"","t_comfort":"","t_eco":"","t_nofrost":"","t_cool":"","t_hysteresis":"","store":"","related":null,"value":"0","last":1613849081695,"lastValue":"1","time":4149662,"change":0},{"_updated":1613240192368,"_created":1539718406108,"active":true,"haddr":"PR.HQP.b47179fa","device":"HQP","io":"o","address":"0I.2","name":"Światło strych","unit":"","eval":null,"type":"","t_comfort":"","t_eco":"","t_nofrost":"","t_cool":"","t_hysteresis":"","store":"","related":["PROM-ADD-4d4dc234"],"value":"0","last":1613240192368,"lastValue":"0","time":10153659,"change":0},{"_updated":1613230038671,"_created":1539781393367,"active":true,"haddr":"PR.HQP.400cb015","device":"HQP","io":"i","address":"0I.1","name":"Klapa na strych","unit":"","eval":null,"type":"0","t_comfort":"","t_eco":"","t_nofrost":"","t_cool":"","t_hysteresis":"","store":"","related":null,"value":"1","last":1613230038671,"lastValue":"0","time":3178223,"change":0},{"_updated":1613887416994,"_created":1539783270193,"haddr":"WHK-5ccf7fc3c3ed-t28ffc1c8851605ac","name":"Temperatura na strychu","device":"WHK","address":"5ccf7fc3c3ed.t.28ffc1c8851605ac","io":"t","value":11.43,"active":true,"unit":"°C⇆","last":1613887416993,"eval":null,"lastValue":11.43,"time":15051,"type":"","t_comfort":"","t_eco":"","t_nofrost":"","t_cool":"","t_hysteresis":"","store":"temp_strych/300","related":null,"_alias":"t_attic","change":1,"unitValue":"11.43 °C↘","sh_type":"","sh_traits":"","sh_nicks":"","t_rel":null},{"_updated":1543239219138,"_created":1540669129487,"active":true,"haddr":"PR.SHL.cd5c77f7","device":"SHL","io":"o","address":"/homekameleon/log.sh","name":"log","unit":"","eval":null,"type":"","t_comfort":"","t_eco":"","t_nofrost":"","t_cool":"","t_hysteresis":"","store":"","related":null,"value":"/sd/reset.txt","last":1543239219136,"lastValue":"/sd/reset.txt","time":20951616,"change":0},{"_updated":1613883630706,"_created":1543082721003,"active":true,"haddr":"PR.VAR.7e379d9a","device":"VAR","io":"o","address":"water_temp","name":"Rodzaj grzania wody","unit":"typ","eval":null,"type":"","t_comfort":"","t_eco":"","t_nofrost":"","t_cool":"","t_hysteresis":"","store":"","related":null,"t_rel":null,"value":"eco","last":1613883630706,"lastValue":"nofrost","time":25822921,"change":0,"unitValue":"nofrost","_alias":"tkcw"},{"_updated":1545051545087,"_created":1545048722296,"active":true,"haddr":"PR.HQP.b54efe58","device":"HQP","io":"i","address":"0P.0","name":"Prąd","unit":"","eval":null,"type":"0","t_comfort":"","t_eco":"","t_nofrost":"","t_cool":"","t_hysteresis":"","store":"","related":null,"t_rel":null,"last":1545051545086,"lastValue":null,"time":104,"change":0,"value":"1"},{"_updated":1561109870515,"_created":1545496759936,"haddr":"WHK-5ccf7fc72374-i1","name":"przycisk A na pilocie","device":"WHK","address":"5ccf7fc72374.i.1","io":"i","value":"1","active":true,"unit":"","eval":null,"type":"","t_comfort":"","t_eco":"","t_nofrost":"","t_cool":"","t_hysteresis":"","store":"","related":null,"t_rel":null,"last":1561109870515,"lastValue":"0","time":436,"change":0},{"_updated":1548016023983,"_created":1545496759940,"haddr":"WHK-5ccf7fc72374-i2","name":"przycisk B na pilocie","device":"WHK","address":"5ccf7fc72374.i.2","io":"i","value":"1","active":true,"unit":"","eval":null,"type":"","t_comfort":"","t_eco":"","t_nofrost":"","t_cool":"","t_hysteresis":"","store":"","related":null,"t_rel":null,"last":1548016023983,"lastValue":"0","time":54,"change":0},{"_updated":1548256639870,"_created":1545496759941,"haddr":"WHK-5ccf7fc72374-i3","name":"przycisk C na pilocie","device":"WHK","address":"5ccf7fc72374.i.3","io":"i","value":"1","active":true,"unit":"","eval":null,"type":"","t_comfort":"","t_eco":"","t_nofrost":"","t_cool":"","t_hysteresis":"","store":"","related":null,"t_rel":null,"last":1548256639869,"lastValue":"0","time":243,"change":0},{"_updated":1613887188777,"_created":1545496759942,"haddr":"WHK-5ccf7fc72374-o1","name":"kaloryfer schody na piętro","device":"WHK","address":"5ccf7fc72374.o.1","io":"o","value":"1","active":true,"unit":"","related":null,"eval":null,"type":"","t_comfort":"","t_eco":"","t_nofrost":"","t_cool":"","t_hysteresis":"","store":"","t_rel":null,"last":1613887188776,"lastValue":"1","time":735557,"change":0},{"_updated":1548255451058,"_created":1545496759944,"haddr":"WHK-5ccf7fc72374-o2","name":"niepewne wyjście","device":"WHK","address":"5ccf7fc72374.o.2","io":"o","value":"0","active":true,"unit":"","related":null,"eval":"","type":"","t_comfort":"","t_eco":"","t_nofrost":"","t_cool":"","t_hysteresis":"","store":"","t_rel":null,"last":1548255235697,"lastValue":"1","time":66086,"change":0},{"_updated":1613887894539,"_created":1545575979760,"haddr":"WHK-5ccf7fc3fcf4-o1","name":"Kaloryfer w sypialni","device":"WHK","address":"5ccf7fc3fcf4.o.1","io":"o","value":"1","active":true,"unit":"","last":1613887894538,"eval":null,"lastValue":"1","time":57102,"change":0,"related":["PR.GRP.1c758ac6"],"type":"","t_comfort":"","t_eco":"","t_nofrost":"","t_cool":"","t_hysteresis":"","store":"","t_rel":null,"sh_type":"","sh_traits":"","sh_nicks":"","_alias":"k_syp"},{"_updated":1545576028964,"_created":1545575979773,"haddr":"WHK-5ccf7fc3fcf4-o2","name":"5ccf7fc3fcf4","device":"WHK","address":"5ccf7fc3fcf4.o.2","io":"o","value":"0","active":true,"unit":"","last":1545576028953,"eval":null,"lastValue":"1","time":9505,"change":0},{"_updated":1613887894495,"_created":1546355410037,"haddr":"WHK-b4e62d30ac8d-o1","name":"Kaloryfer antresola","device":"WHK","address":"b4e62d30ac8d.o.1","io":"o","value":"1","active":true,"unit":"","last":1613887894495,"eval":null,"lastValue":"1","time":60051,"change":0,"type":"","t_comfort":"","t_eco":"","t_nofrost":"","t_cool":"","t_hysteresis":"","store":"","related":null,"t_rel":null},{"_updated":1546355511017,"_created":1546355410041,"haddr":"WHK-b4e62d30ac8d-o2","name":"b4e62d30ac8d","device":"WHK","address":"b4e62d30ac8d.o.2","io":"o","value":"0","active":true,"unit":"","last":1546355511015,"eval":null,"lastValue":"1","time":19384,"change":0},{"_updated":1612207669066,"_created":1559830688144,"active":true,"haddr":"PR.HQP.7d4e7f28","device":"HQP","io":"o","address":"0I.1","name":"Klimatyzator na strychu zależy od wentylatorów","unit":"","eval":null,"type":"","sh_type":"","sh_traits":"","sh_nicks":"","t_comfort":"","t_eco":"","t_nofrost":"","t_cool":"","t_hysteresis":"","store":"","related":null,"t_rel":null,"value":"0","last":1612207669066,"lastValue":"1","time":60966,"change":0,"_alias":"klima"},{"_updated":1613887435154,"_created":1559935691413,"haddr":"WHK-b4e62d30ae38-o1","name":"Wentylator Seba","device":"WHK","address":"b4e62d30ae38.o.1","io":"o","value":"0","active":true,"unit":"","eval":null,"type":"","sh_type":"","sh_traits":"","sh_nicks":"","t_comfort":"","t_eco":"","t_nofrost":"","t_cool":"","t_hysteresis":"","store":"","related":["PR.GRP.29e701c7"],"t_rel":null,"last":1613887435154,"lastValue":"0","time":44772,"change":0},{"_updated":1613887417010,"_created":1559935691414,"haddr":"WHK-b4e62d30ae38-o2","name":"Wentylator strych","device":"WHK","address":"b4e62d30ae38.o.2","io":"o","value":"0","active":true,"unit":"","eval":null,"type":"","sh_type":"","sh_traits":"","sh_nicks":"","t_comfort":"","t_eco":"","t_nofrost":"","t_cool":"","t_hysteresis":"","store":"","related":null,"t_rel":null,"last":1613887417010,"lastValue":"0","time":12047,"change":0},{"_updated":1613886333102,"_created":1559935924413,"haddr":"WHK-84f3eb841e68-o1","name":"Wentylator Marcin","device":"WHK","address":"84f3eb841e68.o.1","io":"o","value":"0","active":true,"unit":"","eval":null,"type":"","sh_type":"","sh_traits":"","sh_nicks":"","t_comfort":"","t_eco":"","t_nofrost":"","t_cool":"","t_hysteresis":"","store":"","related":["PR.GRP.29e701c7"],"t_rel":null,"last":1613886333102,"lastValue":"0","time":43997988,"change":0},{"_updated":1613886333103,"_created":1559935924413,"haddr":"WHK-84f3eb841e68-o2","name":"Wentylator Tomek","device":"WHK","address":"84f3eb841e68.o.2","io":"o","value":"0","active":true,"unit":"","eval":null,"type":"","sh_type":"","sh_traits":"","sh_nicks":"","t_comfort":"","t_eco":"","t_nofrost":"","t_cool":"","t_hysteresis":"","store":"","related":["PR.GRP.29e701c7"],"t_rel":null,"last":1613886333103,"lastValue":"0","time":44000494,"change":0},{"_updated":1559992293124,"_created":1559992008742,"active":true,"haddr":"PR.GRP.29e701c7","device":"GRP","io":"o","address":10,"name":"Wentylatory klimatyzacji strych","unit":"","related":["WHK-b4e62d30ae38-o1","WHK-84f3eb841e68-o1","WHK-84f3eb841e68-o2"],"eval":null,"type":"","sh_type":"","sh_traits":"","sh_nicks":"","t_comfort":"","t_eco":"","t_nofrost":"","t_cool":"","t_hysteresis":"","store":"","t_rel":null,"value":0,"last":1612207668030,"lastValue":0,"time":59999,"change":0},{"_updated":1613886753549,"_created":1574149592412,"active":true,"haddr":"PR.HQP.98aaeae5","device":"HQP","io":"o","address":"0H.4","name":"Dioda wiatrołap","unit":"","eval":null,"type":"","sh_type":"","sh_traits":"","sh_nicks":"","t_comfort":"","t_eco":"","t_nofrost":"","t_cool":"","t_hysteresis":"","store":"","related":null,"t_rel":null,"value":"0","last":1613886753549,"lastValue":"1","time":49362699,"change":0},{"_updated":1613886804223,"_created":1613240138332,"active":true,"haddr":"PR.HQP.a84ea46f","device":"HQP","io":"i","address":"0I.2","name":"Czujka światła","unit":"","eval":null,"type":"0","sh_type":"","sh_traits":"","sh_nicks":"","t_comfort":"","t_eco":"","t_nofrost":"","t_cool":"","t_hysteresis":"","store":"","related":null,"t_rel":null,"value":"0","last":1613886804223,"lastValue":"1","time":49131249,"change":0}]