[{"_updated":1465930641020,"_created":1465930641020,"label":"symbol"},{"_updated":1465930641129,"_created":1465930641129,"label":"Control address"},{"_updated":1465930645145,"_created":1465930645145,"label":"Tags"},{"_updated":1465930624623,"_created":1465930624623,"label":"Global list of inputs"},{"_updated":1465930625012,"_created":1465930625012,"label":"Device"},{"_updated":1465930625223,"_created":1465930625223,"label":"Address"},{"_updated":1465930625228,"_created":1465930625228,"label":"Type"},{"_updated":1465930625228,"_created":1465930625228,"label":"Active"},{"_updated":1466185935654,"_created":1466185935654,"label":"delay"},{"_updated":1463074672141,"_created":1463074672141,"label":"Edit mode"},{"_updated":1463074672477,"_created":1463074672477,"label":"Draw a room"},{"_updated":1463074672478,"_created":1463074672478,"label":"Add devices"},{"_updated":1463074672479,"_created":1463074672479,"label":"Decrease size of devices"},{"_updated":1463074672479,"_created":1463074672479,"label":"Increase size of devices"},{"_updated":1466098959868,"_created":1466098959868,"label":"Device symbol"},{"_updated":1466098959991,"_created":1466098959991,"label":"Power"},{"_updated":1466098960000,"_created":1466098960000,"label":"Alarms"},{"_updated":1466098960010,"_created":1466098960010,"label":"Counters"},{"_updated":1466098960019,"_created":1466098960019,"label":"Lights"},{"_updated":1466098960028,"_created":1466098960028,"label":"Switches"},{"_updated":1466098960037,"_created":1466098960037,"label":"Multimedia"},{"_updated":1466098960045,"_created":1466098960045,"label":"Temperature"},{"_updated":1466098974268,"_created":1466098974268,"label":"Światło"},{"_updated":1466086050758,"_created":1466086050758,"label":"enter label value"},{"_updated":1465930645078,"_created":1465930645078,"label":"Vissible attribute"},{"_updated":1465930645140,"_created":1465930645140,"label":"Attribute"},{"_updated":1465930645142,"_created":1465930645142,"label":"Attribute name[:value1|value2|...]"},{"_updated":1465930645146,"_created":1465930645146,"label":"Space separated tags equivalent to icon names"},{"_updated":1465930645148,"_created":1465930645148,"label":"Input symbol first"},{"_updated":1465930645148,"_created":1465930645148,"label":"Controls"},{"_updated":1466085964238,"_created":1466085964238,"label":"List of application users"},{"_updated":1466085964421,"_created":1466085964421,"label":"Email"},{"_updated":1466085964499,"_created":1466085964499,"label":"Admin"},{"_updated":1465930751031,"_created":1465930751031,"label":"User attributes"},{"_updated":1465930751043,"_created":1465930751043,"label":"First and lastname"},{"_updated":1465930751043,"_created":1465930751043,"label":"Email address"},{"_updated":1465930751045,"_created":1465930751045,"label":"Reset password"},{"_updated":1466185849948,"_created":1466185849948,"label":"Inputs & outputs"},{"_updated":1466185935615,"_created":1466185935615,"label":"I/O"},{"_updated":1466185935585,"_created":1466185935585,"label":"IO"},{"_updated":1466185935625,"_created":1466185935625,"label":"GPF"},{"_updated":1466057826924,"_created":1466057826924,"label":"General Purose Field"},{"_updated":1466185815152,"_created":1466185815152,"label":"Scripts"},{"_updated":1466185815103,"_created":1466185815103,"label":"Global list of scripts"},{"_updated":1466185815122,"_created":1466185815122,"label":"Cond"},{"_updated":1466185815132,"_created":1466185815132,"label":"Act"},{"_updated":1466185935635,"_created":1466185935635,"label":"General Purpose Field"},{"_updated":1466185771714,"_created":1466185771714,"label":"value"},{"_updated":1466185771762,"_created":1466185771762,"label":"Add subscript"},{"_updated":1466185771703,"_created":1466185771703,"label":"Add condition"},{"_updated":1466185771733,"_created":1466185771733,"label":"Add action"},{"_updated":1466078889665,"_created":1466078889665,"label":"Slider attributes"},{"_updated":1466185771655,"_created":1466185771655,"label":"Script conditions"},{"_updated":1466185771743,"_created":1466185771743,"label":"Subscripts"},{"_updated":1466185815142,"_created":1466185815142,"label":"SScr"},{"_updated":1466098952853,"_created":1466098952853,"label":"mouse up"}]